[
  {
    "page_number": 1,
    "bbox": [
      108,
      219,
      384,
      18
    ],
    "text": "PARLIAMENT OF THE DEMOCRATIC",
    "mean_p_confidence": 0.76
  },
  {
    "page_number": 1,
    "bbox": [
      172,
      245,
      265,
      19
    ],
    "text": "SOCIALIST REPUBLIC OF",
    "mean_p_confidence": 0.72
  },
  {
    "page_number": 1,
    "bbox": [
      247,
      274,
      119,
      18
    ],
    "text": "SRI LANKA",
    "mean_p_confidence": 0.63
  },
  {
    "page_number": 1,
    "bbox": [
      129,
      378,
      352,
      19
    ],
    "text": "CONTROL OF PUBLICATIONS ON",
    "mean_p_confidence": 0.76
  },
  {
    "page_number": 1,
    "bbox": [
      170,
      410,
      271,
      23
    ],
    "text": "HORSE-RACING (REPEAL)",
    "mean_p_confidence": 0.62
  },
  {
    "page_number": 1,
    "bbox": [
      201,
      442,
      212,
      20
    ],
    "text": "ACT, No. 31 OF 1987",
    "mean_p_confidence": 0.78
  },
  {
    "page_number": 1,
    "bbox": [
      177,
      556,
      238,
      15
    ],
    "text": "_ (Centified on 16th June, 1987]",
    "mean_p_confidence": 0.52
  },
  {
    "page_number": 1,
    "bbox": [
      180,
      617,
      252,
      16
    ],
    "text": "Printed on the Orders of Governtnent",
    "mean_p_confidence": 0.75
  },
  {
    "page_number": 1,
    "bbox": [
      69,
      707,
      475,
      19
    ],
    "text": "Published as a Supplement to Part 21 of the Gazette of the Democratic",
    "mean_p_confidence": 0.8
  },
  {
    "page_number": 1,
    "bbox": [
      132,
      727,
      331,
      18
    ],
    "text": "Socialist Republic of Sri Lanka of June 19, 1987",
    "mean_p_confidence": 0.84
  },
  {
    "page_number": 1,
    "bbox": [
      122,
      784,
      367,
      11
    ],
    "text": "soo on meme omen",
    "mean_p_confidence": 0.32
  },
  {
    "page_number": 1,
    "bbox": [
      71,
      800,
      472,
      20
    ],
    "text": "= See",
    "mean_p_confidence": 0.28
  },
  {
    "page_number": 1,
    "bbox": [
      69,
      828,
      475,
      16
    ],
    "text": "Price : 30 cents, Postage : 75 cents",
    "mean_p_confidence": 0.75
  },
  {
    "page_number": 2,
    "bbox": [
      93,
      54,
      314,
      14
    ],
    "text": "Control of Publications on Hovse-racit (Repeat)",
    "mean_p_confidence": 0.62
  },
  {
    "page_number": 2,
    "bbox": [
      153,
      55,
      258,
      27
    ],
    "text": "4 anal pian? reed",
    "mean_p_confidence": 0.06
  },
  {
    "page_number": 2,
    "bbox": [
      169,
      96,
      307,
      14
    ],
    "text": "[Certified on 16th June, 1987] .",
    "mean_p_confidence": 0.67
  },
  {
    "page_number": 2,
    "bbox": [
      76,
      122,
      91,
      12
    ],
    "text": "L, D.O. 2/87.",
    "mean_p_confidence": 0.43
  },
  {
    "page_number": 2,
    "bbox": [
      77,
      142,
      375,
      15
    ],
    "text": "(Aw Act 70 RESBAL Tat ConTEOL oF Pusticarions om Honst-",
    "mean_p_confidence": 0.58
  },
  {
    "page_number": 2,
    "bbox": [
      181,
      159,
      168,
      14
    ],
    "text": "macixe Act, No. 44 oF 1961",
    "mean_p_confidence": 0.67
  },
  {
    "page_number": 2,
    "bbox": [
      77,
      185,
      376,
      17
    ],
    "text": "BE it enacted by the Parliament of the Democratic Socialist",
    "mean_p_confidence": 0.86
  },
  {
    "page_number": 2,
    "bbox": [
      78,
      204,
      238,
      15
    ],
    "text": "Republic of Sri Lanka as follows :",
    "mean_p_confidence": 0.57
  },
  {
    "page_number": 2,
    "bbox": [
      90,
      226,
      439,
      16
    ],
    "text": "1L This Act may be cited as the Control of Publications Short title.",
    "mean_p_confidence": 0.79
  },
  {
    "page_number": 2,
    "bbox": [
      77,
      243,
      307,
      16
    ],
    "text": "on Horse-racing (Repeal) Act, No. 31 of 1987.",
    "mean_p_confidence": 0.73
  },
  {
    "page_number": 2,
    "bbox": [
      91,
      270,
      420,
      31
    ],
    "text": "2% The Control of Publications on Horseracing Act, Repeal",
    "mean_p_confidence": 0.77
  },
  {
    "page_number": 2,
    "bbox": [
      74,
      287,
      442,
      25
    ],
    "text": "No, 44 of 1961, is hereby repealed. ga",
    "mean_p_confidence": 0.73
  },
  {
    "page_number": 2,
    "bbox": [
      472,
      310,
      24,
      9
    ],
    "text": "i301.",
    "mean_p_confidence": 0.3
  },
  {
    "page_number": 3,
    "bbox": [
      71,
      797,
      471,
      23
    ],
    "text": "dccuil subscription of Bhis ead Laws of the Parilaman ta iso Cond,",
    "mean_p_confidence": 0.46
  },
  {
    "page_number": 3,
    "bbox": [
      71,
      817,
      471,
      17
    ],
    "text": "Re 200 Corvign}, oayable to the Surmatsrmmar, Govemnemer PuLSCATOns",
    "mean_p_confidence": 0.23
  },
  {
    "page_number": 3,
    "bbox": [
      71,
      830,
      471,
      18
    ],
    "text": "Buwakv, Coconamo 2, before 16th Desember each year in respect of tho year",
    "mean_p_confidence": 0.56
  },
  {
    "page_number": 3,
    "bbox": [
      275,
      848,
      56,
      13
    ],
    "text": "following.",
    "mean_p_confidence": 0.17
  }
]