[
  {
    "page_number": 1,
    "bbox": [
      297,
      39,
      87,
      17
    ],
    "text": "ES) .",
    "mean_p_confidence": 0.14
  },
  {
    "page_number": 1,
    "bbox": [
      108,
      204,
      393,
      26
    ],
    "text": "PARLIAMENT OF THE DEMOCRATIC",
    "mean_p_confidence": 0.76
  },
  {
    "page_number": 1,
    "bbox": [
      176,
      239,
      375,
      26
    ],
    "text": "SOCIALIST REPUBLIC OF - .",
    "mean_p_confidence": 0.49
  },
  {
    "page_number": 1,
    "bbox": [
      247,
      272,
      156,
      26
    ],
    "text": "SRI LANKA,",
    "mean_p_confidence": -0.0
  },
  {
    "page_number": 1,
    "bbox": [
      106,
      354,
      395,
      19
    ],
    "text": "FISHERMENS PENSION: AND SOCIAL",
    "mean_p_confidence": 0.7
  },
  {
    "page_number": 1,
    "bbox": [
      147,
      383,
      332,
      21
    ],
    "text": "SECURITY BENEFIT SCHEME -",
    "mean_p_confidence": 0.74
  },
  {
    "page_number": 1,
    "bbox": [
      158,
      415,
      264,
      28
    ],
    "text": "~ AGT, No. 23 OF 1990 *.",
    "mean_p_confidence": 0.53
  },
  {
    "page_number": 1,
    "bbox": [
      173,
      510,
      254,
      36
    ],
    "text": "\\ [Certified on 29th June, 1990) .",
    "mean_p_confidence": 0.54
  },
  {
    "page_number": 1,
    "bbox": [
      76,
      582,
      346,
      22
    ],
    "text": ": Printed on the Orders of Government",
    "mean_p_confidence": 0.81
  },
  {
    "page_number": 1,
    "bbox": [
      61,
      667,
      474,
      28
    ],
    "text": "Published as Supplement to Part Il ofthe Gazette of the Democratic",
    "mean_p_confidence": 0.65
  },
  {
    "page_number": 1,
    "bbox": [
      132,
      697,
      337,
      18
    ],
    "text": "Socialist Republic of Sri Lanka of June 29, 1990",
    "mean_p_confidence": 0.84
  },
  {
    "page_number": 1,
    "bbox": [
      114,
      773,
      369,
      14
    ],
    "text": "(FRDCTED AT Twit DEPARTMENT OF COVEANDSENT PRINTING, SRE LANKA",
    "mean_p_confidence": 0.41
  },
  {
    "page_number": 1,
    "bbox": [
      97,
      806,
      407,
      12
    ],
    "text": "70 me FORTGID AE PIP COVRAMTOET FUSEICATIOWS WHEN, ooLeam0",
    "mean_p_confidence": 0.21
  },
  {
    "page_number": 1,
    "bbox": [
      60,
      834,
      482,
      20
    ],
    "text": "Brice : Re, 1.20 Postage Re. 1.08",
    "mean_p_confidence": 0.56
  },
  {
    "page_number": 2,
    "bbox": [
      73,
      30,
      361,
      14
    ],
    "text": "Fishermen's Pension and Social Security Benefit Scheme",
    "mean_p_confidence": 0.72
  },
  {
    "page_number": 2,
    "bbox": [
      192,
      44,
      332,
      17
    ],
    "text": "Act, No. 23 of 1990 . .",
    "mean_p_confidence": 0.52
  },
  {
    "page_number": 2,
    "bbox": [
      92,
      72,
      256,
      14
    ],
    "text": ". [Certified on 29th June, 1990]",
    "mean_p_confidence": 0.61
  },
  {
    "page_number": 2,
    "bbox": [
      61,
      101,
      351,
      13
    ],
    "text": "1, DO 40/88, Lo",
    "mean_p_confidence": 0.4
  },
  {
    "page_number": 2,
    "bbox": [
      62,
      124,
      385,
      12
    ],
    "text": "AN ACT TO PROVIDE FORTHE ESTAPLIEAMENT OF A PeNGION AND",
    "mean_p_confidence": 0.59
  },
  {
    "page_number": 2,
    "bbox": [
      75,
      140,
      412,
      14
    ],
    "text": "Soctan Secummy Bextert Scueme ron Frstenmun; 10",
    "mean_p_confidence": 0.36
  },
  {
    "page_number": 2,
    "bbox": [
      75,
      157,
      371,
      11
    ],
    "text": "PROVIDE FOR THE OPERATION OF THE ScHEME bx Tmt Aoat-",
    "mean_p_confidence": 0.53
  },
  {
    "page_number": 2,
    "bbox": [
      74,
      175,
      371,
      12
    ],
    "text": "CULTURAL INSURANCE BOARD; AND TO PROVIDE FOR MATTERS",
    "mean_p_confidence": 0.71
  },
  {
    "page_number": 2,
    "bbox": [
      76,
      192,
      399,
      10
    ],
    "text": "CONNECTED THERWITH OR INCIUENTAL THERETO .",
    "mean_p_confidence": 0.41
  },
  {
    "page_number": 2,
    "bbox": [
      62,
      226,
      383,
      14
    ],
    "text": "BE it enacted by the Parliament of the Democratic Socialist",
    "mean_p_confidence": 0.81
  },
  {
    "page_number": 2,
    "bbox": [
      62,
      244,
      239,
      13
    ],
    "text": "Republic of Sri Lanka as follows :",
    "mean_p_confidence": 0.75
  },
  {
    "page_number": 2,
    "bbox": [
      78,
      264,
      471,
      22
    ],
    "text": "1. This Act may be cited as the Fishermens Pension and Short :",
    "mean_p_confidence": 0.74
  },
  {
    "page_number": 2,
    "bbox": [
      64,
      284,
      475,
      15
    ],
    "text": "Social Security Benefit Scheme Act, No. 23 of 1900 and gna :",
    "mean_p_confidence": 0.72
  },
  {
    "page_number": 2,
    "bbox": [
      63,
      299,
      452,
      22
    ],
    "text": "shall come into operation on such date es may be appointed SSS",
    "mean_p_confidence": 0.76
  },
  {
    "page_number": 2,
    "bbox": [
      65,
      325,
      329,
      15
    ],
    "text": "by the Minister hy Order published in the Gazerte.",
    "mean_p_confidence": 0.76
  },
  {
    "page_number": 2,
    "bbox": [
      212,
      343,
      318,
      11
    ],
    "text": ". x .",
    "mean_p_confidence": 0.36
  },
  {
    "page_number": 2,
    "bbox": [
      229,
      361,
      163,
      12
    ],
    "text": "PARTI .",
    "mean_p_confidence": 0.31
  },
  {
    "page_number": 2,
    "bbox": [
      79,
      385,
      355,
      13
    ],
    "text": "JESTARLISHMENT OF TH FISHERMEN'S PENSIoN ANU SOCEAL",
    "mean_p_confidence": 0.22
  },
  {
    "page_number": 2,
    "bbox": [
      173,
      402,
      185,
      12
    ],
    "text": "Sreumy Bewsre Sexmme -",
    "mean_p_confidence": 0.08
  },
  {
    "page_number": 2,
    "bbox": [
      81,
      432,
      434,
      15
    ],
    "text": "2, There shall be established according to the provisions Establish",
    "mean_p_confidence": 0.81
  },
  {
    "page_number": 2,
    "bbox": [
      66,
      449,
      461,
      30
    ],
    "text": "of this Act, a scheme which shall be called the Fishermen's of the vs",
    "mean_p_confidence": 0.75
  },
  {
    "page_number": 2,
    "bbox": [
      67,
      473,
      437,
      16
    ],
    "text": "Pension and Social Security Beneflt Scheme (hereinafter pension",
    "mean_p_confidence": 0.79
  },
  {
    "page_number": 2,
    "bbox": [
      68,
      485,
      472,
      29
    ],
    "text": "referred to ag the Scheme). Pa :",
    "mean_p_confidence": 0.53
  },
  {
    "page_number": 2,
    "bbox": [
      461,
      511,
      47,
      11
    ],
    "text": "Security",
    "mean_p_confidence": 0.32
  },
  {
    "page_number": 2,
    "bbox": [
      461,
      522,
      39,
      10
    ],
    "text": "Benet",
    "mean_p_confidence": -0.01
  },
  {
    "page_number": 2,
    "bbox": [
      313,
      534,
      193,
      13
    ],
    "text": "~. Scheme.",
    "mean_p_confidence": 0.2
  },
  {
    "page_number": 2,
    "bbox": [
      83,
      551,
      455,
      32
    ],
    "text": "3 The objects of the Scheme shall be Bees i:",
    "mean_p_confidence": 0.65
  },
  {
    "page_number": 2,
    "bbox": [
      83,
      578,
      455,
      22
    ],
    "text": "(@) to provide social security to fishermen during their ofthe =.",
    "mean_p_confidence": 0.75
  },
  {
    "page_number": 2,
    "bbox": [
      121,
      602,
      413,
      14
    ],
    "text": "old age or disability ; -",
    "mean_p_confidence": 0.59
  },
  {
    "page_number": 2,
    "bbox": [
      83,
      621,
      363,
      16
    ],
    "text": "() to provide rellet to the dependents of fishermen upon",
    "mean_p_confidence": 0.82
  },
  {
    "page_number": 2,
    "bbox": [
      120,
      639,
      193,
      12
    ],
    "text": "the death of such fishermen ;",
    "mean_p_confidence": 0.78
  },
  {
    "page_number": 2,
    "bbox": [
      84,
      657,
      363,
      18
    ],
    "text": "(c) to encourage fishermen to continue in thelr occupa-",
    "mean_p_confidence": 0.72
  },
  {
    "page_number": 2,
    "bbox": [
      121,
      676,
      102,
      15
    ],
    "text": "tion 5 .",
    "mean_p_confidence": 0.25
  },
  {
    "page_number": 2,
    "bbox": [
      84,
      694,
      364,
      19
    ],
    "text": "{d) to attract young persons to the fishing industry; and",
    "mean_p_confidence": 0.78
  },
  {
    "page_number": 2,
    "bbox": [
      84,
      715,
      365,
      19
    ],
    "text": "{e) te inculeate the habit of saving and to promote thrist",
    "mean_p_confidence": 0.83
  },
  {
    "page_number": 2,
    "bbox": [
      122,
      736,
      137,
      14
    ],
    "text": "among the fishermen:",
    "mean_p_confidence": 0.67
  },
  {
    "page_number": 2,
    "bbox": [
      85,
      762,
      428,
      16
    ],
    "text": "4. The Minister may, having regard to the feasibility of Area of",
    "mean_p_confidence": 0.79
  },
  {
    "page_number": 2,
    "bbox": [
      70,
      776,
      450,
      24
    ],
    "text": "administering the Scheme and the occupational hazards in \"Pine\"",
    "mean_p_confidence": 0.67
  },
  {
    "page_number": 2,
    "bbox": [
      72,
      800,
      439,
      22
    ],
    "text": "any type of fishing, ky Order published in the Gazette, Scheme",
    "mean_p_confidence": 0.79
  },
  {
    "page_number": 2,
    "bbox": [
      72,
      819,
      467,
      31
    ],
    "text": "determine the area in which the Scheme shall operate, fegnined",
    "mean_p_confidence": 0.76
  },
  {
    "page_number": 3,
    "bbox": [
      85,
      33,
      455,
      21
    ],
    "text": "7 2 Fishermen's Pension and Social Security Benefit Schema",
    "mean_p_confidence": 0.66
  },
  {
    "page_number": 3,
    "bbox": [
      197,
      55,
      223,
      17
    ],
    "text": ". Act, No, 23 of 1990",
    "mean_p_confidence": 0.72
  },
  {
    "page_number": 3,
    "bbox": [
      70,
      82,
      484,
      27
    ],
    "text": "Bligibitity 5. (1) Subject to the provisions of subsection (2), any:",
    "mean_p_confidence": 0.74
  },
  {
    "page_number": 3,
    "bbox": [
      70,
      99,
      486,
      21
    ],
    "text": "fo-icin. fisherman who ia not Jess than eighteen years of age and",
    "mean_p_confidence": 0.71
  },
  {
    "page_number": 3,
    "bbox": [
      69,
      109,
      492,
      31
    ],
    "text": "Scheme, not more than fifty nine years of age shall be entitled to-",
    "mean_p_confidence": 0.82
  },
  {
    "page_number": 3,
    "bbox": [
      79,
      158,
      477,
      21
    ],
    "text": ". _ For the purpose of this subsetion fisherman means any",
    "mean_p_confidence": 0.66
  },
  {
    "page_number": 3,
    "bbox": [
      167,
      182,
      390,
      15
    ],
    "text": "person who makes his living by fishing or fish farming,",
    "mean_p_confidence": 0.81
  },
  {
    "page_number": 3,
    "bbox": [
      167,
      198,
      357,
      16
    ],
    "text": "whether in the sea, lagoons or inland bodies of water.",
    "mean_p_confidence": 0.86
  },
  {
    "page_number": 3,
    "bbox": [
      184,
      231,
      374,
      15
    ],
    "text": "(2) The following persons shall not be entitled to join",
    "mean_p_confidence": 0.81
  },
  {
    "page_number": 3,
    "bbox": [
      151,
      249,
      149,
      18
    ],
    "text": "__ the Scheme:*",
    "mean_p_confidence": 0.28
  },
  {
    "page_number": 3,
    "bbox": [
      185,
      271,
      374,
      20
    ],
    "text": "(a) am owner of three or more machanized Loats, the",
    "mean_p_confidence": 0.74
  },
  {
    "page_number": 3,
    "bbox": [
      102,
      294,
      458,
      19
    ],
    "text": ". + combined weight of which exceeds six tons gross ;",
    "mean_p_confidence": 0.63
  },
  {
    "page_number": 3,
    "bbox": [
      126,
      316,
      434,
      20
    ],
    "text": "() an owner of one or more fish farms, the total extent",
    "mean_p_confidence": 0.75
  },
  {
    "page_number": 3,
    "bbox": [
      223,
      339,
      343,
      14
    ],
    "text": "of which exceeds five ucres; :",
    "mean_p_confidence": 0.6
  },
  {
    "page_number": 3,
    "bbox": [
      186,
      363,
      378,
      19
    ],
    "text": "() @ person who by reason of his employment is entitled",
    "mean_p_confidence": 0.79
  },
  {
    "page_number": 3,
    "bbox": [
      223,
      384,
      337,
      14
    ],
    "text": "to receive a pension or benefits under the Employees",
    "mean_p_confidence": 0.75
  },
  {
    "page_number": 3,
    "bbox": [
      123,
      401,
      436,
      15
    ],
    "text": ". + Provident Fund established by the Employees Pro-",
    "mean_p_confidence": 0.71
  },
  {
    "page_number": 3,
    "bbox": [
      225,
      418,
      299,
      17
    ],
    "text": "vident Fund Act, No, 15 of 1958; .",
    "mean_p_confidence": 0.74
  },
  {
    "page_number": 3,
    "bbox": [
      162,
      447,
      400,
      14
    ],
    "text": "+ (@) @ person liable ta pay income tax; .",
    "mean_p_confidence": 0.69
  },
  {
    "page_number": 3,
    "bbox": [
      162,
      476,
      379,
      16
    ],
    "text": "|. ) a person who is in receipt of a pension; of",
    "mean_p_confidence": 0.65
  },
  {
    "page_number": 3,
    "bbox": [
      109,
      500,
      452,
      15
    ],
    "text": "- +f) a person who iz entitled to receive a pension on the",
    "mean_p_confidence": 0.65
  },
  {
    "page_number": 3,
    "bbox": [
      102,
      516,
      463,
      22
    ],
    "text": "LE Le death of hia spouse. .",
    "mean_p_confidence": 0.33
  },
  {
    "page_number": 3,
    "bbox": [
      78,
      556,
      483,
      16
    ],
    "text": "Benefia 6 (4) A fisherman who joins the Scheme. (hereinafter",
    "mean_p_confidence": 0.65
  },
  {
    "page_number": 3,
    "bbox": [
      79,
      567,
      483,
      22
    ],
    "text": "Wit geferted to as the contributor) shell be entitlet to the",
    "mean_p_confidence": 0.7
  },
  {
    "page_number": 3,
    "bbox": [
      61,
      590,
      501,
      16
    ],
    "text": "Bcheme, following benefits under the Scheme celculated on such",
    "mean_p_confidence": 0.69
  },
  {
    "page_number": 3,
    "bbox": [
      178,
      608,
      266,
      14
    ],
    "text": "basis os may be prescrihed : .",
    "mean_p_confidence": 0.59
  },
  {
    "page_number": 3,
    "bbox": [
      85,
      633,
      431,
      14
    ],
    "text": "eo G@) a perlodical pensich of a prescribed amount ;",
    "mean_p_confidence": 0.51
  },
  {
    "page_number": 3,
    "bbox": [
      193,
      658,
      370,
      14
    ],
    "text": "() In case of perinanent partial disablement, a lump sum",
    "mean_p_confidence": 0.71
  },
  {
    "page_number": 3,
    "bbox": [
      137,
      675,
      385,
      14
    ],
    "text": "- gratuity of a pension when it becomes due ;",
    "mean_p_confidence": 0.68
  },
  {
    "page_number": 3,
    "bbox": [
      194,
      699,
      369,
      15
    ],
    "text": "() im case of permanent total disablement, a tump sum",
    "mean_p_confidence": 0.72
  },
  {
    "page_number": 3,
    "bbox": [
      203,
      714,
      361,
      19
    ],
    "text": "| gratuity or periodical aUowance of a prescribed",
    "mean_p_confidence": 0.6
  },
  {
    "page_number": 3,
    "bbox": [
      223,
      735,
      274,
      16
    ],
    "text": "_ ammount | or . 5",
    "mean_p_confidence": 0.39
  },
  {
    "page_number": 3,
    "bbox": [
      144,
      753,
      184,
      19
    ],
    "text": "~ 44) a death gratuity,",
    "mean_p_confidence": 0.49
  },
  {
    "page_number": 3,
    "bbox": [
      138,
      788,
      427,
      21
    ],
    "text": "+. (@) The basis of calculating a pension or gratuity shall",
    "mean_p_confidence": 0.68
  },
  {
    "page_number": 3,
    "bbox": [
      140,
      809,
      429,
      17
    ],
    "text": "\\ \"be ppreseribed taking into consideration, inter alia, the",
    "mean_p_confidence": 0.53
  },
  {
    "page_number": 3,
    "bbox": [
      180,
      825,
      386,
      18
    ],
    "text": "perlod of contribution, the age af the contributor and the",
    "mean_p_confidence": 0.78
  },
  {
    "page_number": 3,
    "bbox": [
      122,
      844,
      404,
      18
    ],
    "text": ", / | wmount of contributions made by the contributor. |",
    "mean_p_confidence": 0.49
  },
  {
    "page_number": 4,
    "bbox": [
      75,
      27,
      373,
      13
    ],
    "text": "Fishermen's Pension and Social Security Benefit Scheme 8",
    "mean_p_confidence": 0.8
  },
  {
    "page_number": 4,
    "bbox": [
      194,
      43,
      119,
      14
    ],
    "text": "Act, No. 28 of 1990",
    "mean_p_confidence": 0.71
  },
  {
    "page_number": 4,
    "bbox": [
      77,
      76,
      419,
      13
    ],
    "text": "7. (2) A contributor shall be entitled toa pension when",
    "mean_p_confidence": 0.73
  },
  {
    "page_number": 4,
    "bbox": [
      62,
      91,
      443,
      15
    ],
    "text": "on reaching the age of sixty years. A contributor who com-, pension",
    "mean_p_confidence": 0.79
  },
  {
    "page_number": 4,
    "bbox": [
      63,
      105,
      476,
      21
    ],
    "text": "mences to contribute after reaching the age of fifty-five Payable,",
    "mean_p_confidence": 0.78
  },
  {
    "page_number": 4,
    "bbox": [
      62,
      126,
      385,
      13
    ],
    "text": "years shall, however, be entitled toa pension only after pay>",
    "mean_p_confidence": 0.8
  },
  {
    "page_number": 4,
    "bbox": [
      62,
      142,
      384,
      14
    ],
    "text": "ing his entire contribution as may be prescribed and at the",
    "mean_p_confidence": 0.86
  },
  {
    "page_number": 4,
    "bbox": [
      62,
      159,
      377,
      14
    ],
    "text": "end of five years from the date of his joining the Scheme.",
    "mean_p_confidence": 0.86
  },
  {
    "page_number": 4,
    "bbox": [
      69,
      187,
      376,
      15
    ],
    "text": "+ (2) The pension shaill be paid upto the end of the month",
    "mean_p_confidence": 0.79
  },
  {
    "page_number": 4,
    "bbox": [
      62,
      205,
      242,
      11
    ],
    "text": "in which the contributor dies. :",
    "mean_p_confidence": 0.68
  },
  {
    "page_number": 4,
    "bbox": [
      78,
      237,
      439,
      15
    ],
    "text": "8. The Minister may, with a view to encouraging fisher- Rebate on",
    "mean_p_confidence": 0.78
  },
  {
    "page_number": 4,
    "bbox": [
      64,
      250,
      449,
      20
    ],
    "text": "men to join the Scheme prescribe either a rebate or a {opiribu-",
    "mean_p_confidence": 0.78
  },
  {
    "page_number": 4,
    "bbox": [
      64,
      269,
      362,
      14
    ],
    "text": "Aiseount on the contributions to be paid ky contributors.",
    "mean_p_confidence": 0.71
  },
  {
    "page_number": 4,
    "bbox": [
      78,
      297,
      457,
      18
    ],
    "text": "9. Any contributor who is permanently and partially Partial",
    "mean_p_confidence": 0.68
  },
  {
    "page_number": 4,
    "bbox": [
      64,
      314,
      466,
      17
    ],
    "text": "disabled before he becomes entitled'to receive his pension Sisablement.",
    "mean_p_confidence": 0.73
  },
  {
    "page_number": 4,
    "bbox": [
      64,
      334,
      408,
      14
    ],
    "text": "shail, at hls option, receive disablement gratuity under",
    "mean_p_confidence": 0.5
  },
  {
    "page_number": 4,
    "bbox": [
      64,
      350,
      381,
      13
    ],
    "text": "the Scheme calculated on the prescribed basis and leave",
    "mean_p_confidence": 0.79
  },
  {
    "page_number": 4,
    "bbox": [
      64,
      366,
      428,
      13
    ],
    "text": "the Scheme or remain in the Scheme without paying any :",
    "mean_p_confidence": 0.73
  },
  {
    "page_number": 4,
    "bbox": [
      65,
      381,
      466,
      15
    ],
    "text": "further contribution and receive the penston when it be- :",
    "mean_p_confidence": 0.78
  },
  {
    "page_number": 4,
    "bbox": [
      64,
      398,
      198,
      16
    ],
    "text": "somes due. .",
    "mean_p_confidence": 0.44
  },
  {
    "page_number": 4,
    "bbox": [
      79,
      429,
      408,
      15
    ],
    "text": "10, Any contributer who is permanently and totally Total",
    "mean_p_confidence": 0.71
  },
  {
    "page_number": 4,
    "bbox": [
      65,
      442,
      462,
      17
    ],
    "text": "disabled before he becomes enttiled to receive his pension *isnblemant.",
    "mean_p_confidence": 0.67
  },
  {
    "page_number": 4,
    "bbox": [
      65,
      461,
      380,
      15
    ],
    "text": "shall, at his option, receive a disablement gratuity under",
    "mean_p_confidence": 0.82
  },
  {
    "page_number": 4,
    "bbox": [
      66,
      477,
      460,
      14
    ],
    "text": "the Scheme celoulated on the preseribed basis and leave .",
    "mean_p_confidence": 0.65
  },
  {
    "page_number": 4,
    "bbox": [
      65,
      493,
      380,
      13
    ],
    "text": "the Scheme or receive a disablement allowance for life",
    "mean_p_confidence": 0.72
  },
  {
    "page_number": 4,
    "bbox": [
      65,
      509,
      380,
      14
    ],
    "text": "under the Scheme calculated on the prescribed basis and",
    "mean_p_confidence": 0.76
  },
  {
    "page_number": 4,
    "bbox": [
      65,
      525,
      380,
      15
    ],
    "text": "remain in the Scheme without paying any further contri-",
    "mean_p_confidence": 0.84
  },
  {
    "page_number": 4,
    "bbox": [
      64,
      543,
      44,
      11
    ],
    "text": "bution.",
    "mean_p_confidence": 0.45
  },
  {
    "page_number": 4,
    "bbox": [
      80,
      569,
      410,
      16
    ],
    "text": "11, In the event of the death of a contributor before he Deuth",
    "mean_p_confidence": 0.73
  },
  {
    "page_number": 4,
    "bbox": [
      65,
      583,
      440,
      17
    ],
    "text": "becomes entitled to receive his pension a death gratuity Ststuity.",
    "mean_p_confidence": 0.71
  },
  {
    "page_number": 4,
    "bbox": [
      65,
      603,
      380,
      13
    ],
    "text": "under the Scheme calculated on such basis as may be",
    "mean_p_confidence": 0.83
  },
  {
    "page_number": 4,
    "bbox": [
      65,
      620,
      380,
      13
    ],
    "text": "Prescribed shall be patd to his surviving.spouse and failing",
    "mean_p_confidence": 0.68
  },
  {
    "page_number": 4,
    "bbox": [
      65,
      636,
      411,
      14
    ],
    "text": "auch spouse to one only of the relatives hy blood of such",
    "mean_p_confidence": 0.78
  },
  {
    "page_number": 4,
    "bbox": [
      65,
      652,
      380,
      13
    ],
    "text": "cobtributor in the order of priority set cut in the Schedule",
    "mean_p_confidence": 0.82
  },
  {
    "page_number": 4,
    "bbox": [
      65,
      668,
      469,
      16
    ],
    "text": "to this Act the older being preferred to the younger where.",
    "mean_p_confidence": 0.79
  },
  {
    "page_number": 4,
    "bbox": [
      65,
      685,
      343,
      13
    ],
    "text": "there are more relatives than one in any group. -",
    "mean_p_confidence": 0.78
  },
  {
    "page_number": 4,
    "bbox": [
      74,
      713,
      364,
      14
    ],
    "text": ". . PART :",
    "mean_p_confidence": 0.28
  },
  {
    "page_number": 4,
    "bbox": [
      161,
      737,
      290,
      21
    ],
    "text": "Manacemanr or nm Sem | :",
    "mean_p_confidence": 0.28
  },
  {
    "page_number": 4,
    "bbox": [
      79,
      765,
      454,
      20
    ],
    "text": "12, The Agricultural Insurance Bosrd established under q sicultural",
    "mean_p_confidence": 0.51
  },
  {
    "page_number": 4,
    "bbox": [
      65,
      785,
      464,
      16
    ],
    "text": "the Agricultural Insurance Law, No. 27'of 1973 (herein. Insurance .",
    "mean_p_confidence": 0.62
  },
  {
    "page_number": 4,
    "bbox": [
      59,
      799,
      453,
      25
    ],
    "text": "_ after referred to az the Board \")' shall operate the Scheme Boars?",
    "mean_p_confidence": 0.64
  },
  {
    "page_number": 4,
    "bbox": [
      66,
      824,
      418,
      14
    ],
    "text": "in. consultation with the Minister. the",
    "mean_p_confidence": 0.54
  },
  {
    "page_number": 5,
    "bbox": [
      162,
      28,
      411,
      23
    ],
    "text": "4 Fishermwa Pension and Social Security Benefit Scheme",
    "mean_p_confidence": 0.67
  },
  {
    "page_number": 5,
    "bbox": [
      244,
      53,
      169,
      14
    ],
    "text": ". Act, No. 25:0f 1980",
    "mean_p_confidence": 0.54
  },
  {
    "page_number": 5,
    "bbox": [
      64,
      84,
      483,
      20
    ],
    "text": "BOeE 13 The Board shall in addition to the powers conferred",
    "mean_p_confidence": 0.72
  },
  {
    "page_number": 5,
    "bbox": [
      67,
      102,
      481,
      17
    ],
    "text": "ai _ gait by the Agricultural Insurance Law, No. 27 of 19%,",
    "mean_p_confidence": 0.74
  },
  {
    "page_number": 5,
    "bbox": [
      63,
      114,
      429,
      28
    ],
    "text": "functions . bave the following powers, functions and duties :.",
    "mean_p_confidence": 0.61
  },
  {
    "page_number": 5,
    "bbox": [
      68,
      136,
      482,
      28
    ],
    "text": "Board. + (a) to make rules in respect of the administration of",
    "mean_p_confidence": 0.72
  },
  {
    "page_number": 5,
    "bbox": [
      216,
      158,
      334,
      14
    ],
    "text": "the affairs of the Board with regard to the Scheme ;",
    "mean_p_confidence": 0.81
  },
  {
    "page_number": 5,
    "bbox": [
      180,
      182,
      371,
      14
    ],
    "text": "(b) to refer to the Advisory Committee for advice any",
    "mean_p_confidence": 0.83
  },
  {
    "page_number": 5,
    "bbox": [
      217,
      199,
      222,
      14
    ],
    "text": "matfer pertaining, tn the Scheme ;",
    "mean_p_confidence": 0.57
  },
  {
    "page_number": 5,
    "bbox": [
      151,
      221,
      401,
      15
    ],
    "text": "+ (c) to msintain the required actuarial, ficancial and",
    "mean_p_confidence": 0.68
  },
  {
    "page_number": 5,
    "bbox": [
      193,
      239,
      332,
      14
    ],
    "text": "~ -aperational teports in respect of the Scheme;",
    "mean_p_confidence": 0.63
  },
  {
    "page_number": 5,
    "bbox": [
      103,
      259,
      450,
      17
    ],
    "text": ": (@ 10 moniter, evaluate and review the Scheme and",
    "mean_p_confidence": 0.71
  },
  {
    "page_number": 5,
    "bbox": [
      155,
      277,
      399,
      15
    ],
    "text": ": effect changes in the operational rules where",
    "mean_p_confidence": 0.62
  },
  {
    "page_number": 5,
    "bbox": [
      219,
      294,
      321,
      15
    ],
    "text": "necessary and where it is empowered to do 50;",
    "mean_p_confidence": 0.85
  },
  {
    "page_number": 5,
    "bbox": [
      183,
      317,
      372,
      16
    ],
    "text": "( to determine the benefits to be paid to any contri-",
    "mean_p_confidence": 0.8
  },
  {
    "page_number": 5,
    "bbox": [
      178,
      335,
      214,
      13
    ],
    "text": "> butor under the Scheme ;",
    "mean_p_confidence": 0.63
  },
  {
    "page_number": 5,
    "bbox": [
      184,
      358,
      371,
      15
    ],
    "text": "(f) to employ officers, servants and other employees as",
    "mean_p_confidence": 0.66
  },
  {
    "page_number": 5,
    "bbox": [
      222,
      373,
      333,
      16
    ],
    "text": "are necessary for the efficient management of the",
    "mean_p_confidence": 0.79
  },
  {
    "page_number": 5,
    "bbox": [
      224,
      392,
      261,
      13
    ],
    "text": "Scheme; shd .",
    "mean_p_confidence": 0.58
  },
  {
    "page_number": 5,
    "bbox": [
      187,
      413,
      369,
      16
    ],
    "text": "(g) to do all other things which in the opinion of the",
    "mean_p_confidence": 0.86
  },
  {
    "page_number": 5,
    "bbox": [
      144,
      429,
      413,
      16
    ],
    "text": ". Board are necessary to facilitate the operation and",
    "mean_p_confidence": 0.76
  },
  {
    "page_number": 5,
    "bbox": [
      91,
      448,
      322,
      15
    ],
    "text": ": . management of the Scheme.",
    "mean_p_confidence": 0.54
  },
  {
    "page_number": 5,
    "bbox": [
      75,
      470,
      481,
      36
    ],
    "text": "Delegation 44. (1) The Board may delegate to the Chairman or any",
    "mean_p_confidence": 0.76
  },
  {
    "page_number": 5,
    "bbox": [
      76,
      494,
      482,
      20
    ],
    "text": "functors other member of the Board or any officer af the Board any",
    "mean_p_confidence": 0.74
  },
  {
    "page_number": 5,
    "bbox": [
      73,
      513,
      421,
      29
    ],
    "text": "Pee of iff powers, functions or duties undar sertion 13.",
    "mean_p_confidence": 0.7
  },
  {
    "page_number": 5,
    "bbox": [
      78,
      540,
      481,
      26
    ],
    "text": "Soe. (2) The Chairman, a member or an officer to whom any",
    "mean_p_confidence": 0.69
  },
  {
    "page_number": 5,
    "bbox": [
      176,
      567,
      382,
      16
    ],
    "text": "of the powers, functions or duties of the Board have been",
    "mean_p_confidence": 0.86
  },
  {
    "page_number": 5,
    "bbox": [
      177,
      589,
      382,
      15
    ],
    "text": "delegated under subsection (1) shall exereise, perform or",
    "mean_p_confidence": 0.76
  },
  {
    "page_number": 5,
    "bbox": [
      177,
      608,
      382,
      17
    ],
    "text": "discharge such powers, functions or duties subject to the",
    "mean_p_confidence": 0.85
  },
  {
    "page_number": 5,
    "bbox": [
      156,
      631,
      218,
      14
    ],
    "text": "._\"eneral direction of the Hoard;",
    "mean_p_confidence": 0.61
  },
  {
    "page_number": 5,
    "bbox": [
      81,
      655,
      479,
      31
    ],
    "text": "Board . 45. The Bostd shall on enrolment of any person as a",
    "mean_p_confidence": 0.7
  },
  {
    "page_number": 5,
    "bbox": [
      82,
      675,
      478,
      32
    ],
    "text": "eit contributor issue him with's policy setting. out the",
    "mean_p_confidence": 0.6
  },
  {
    "page_number": 5,
    "bbox": [
      80,
      699,
      480,
      29
    ],
    "text": "gach con contributions to be made by him, the terms and conditions",
    "mean_p_confidence": 0.77
  },
  {
    "page_number": 5,
    "bbox": [
      180,
      723,
      381,
      17
    ],
    "text": "cf the polley and the benefits to which he ds entitled under",
    "mean_p_confidence": 0.79
  },
  {
    "page_number": 5,
    "bbox": [
      181,
      746,
      157,
      14
    ],
    "text": "the policy issued to him.",
    "mean_p_confidence": 0.78
  },
  {
    "page_number": 5,
    "bbox": [
      84,
      776,
      478,
      26
    ],
    "text": "Forteture . . 18 (1) The date before which contributions are paysble",
    "mean_p_confidence": 0.6
  },
  {
    "page_number": 5,
    "bbox": [
      84,
      795,
      478,
      19
    ],
    "text": "ofpelioy: by a contributor shall be specified in the policy and any",
    "mean_p_confidence": 0.75
  },
  {
    "page_number": 5,
    "bbox": [
      182,
      819,
      381,
      16
    ],
    "text": "contributor who fails to pay ten consecutive instalments",
    "mean_p_confidence": 0.76
  },
  {
    "page_number": 5,
    "bbox": [
      181,
      839,
      364,
      18
    ],
    "text": "shall forfeit the benefits under the policy issued to hirt.",
    "mean_p_confidence": 0.79
  },
  {
    "page_number": 6,
    "bbox": [
      83,
      30,
      374,
      15
    ],
    "text": "Fishermens Pension and Social Security Benefit Scheme 5",
    "mean_p_confidence": 0.82
  },
  {
    "page_number": 6,
    "bbox": [
      203,
      47,
      119,
      14
    ],
    "text": "Act, No. 28 of 1990",
    "mean_p_confidence": 0.71
  },
  {
    "page_number": 6,
    "bbox": [
      87,
      79,
      370,
      15
    ],
    "text": "@) Where any contributor has forfeited tho benefits",
    "mean_p_confidence": 0.77
  },
  {
    "page_number": 6,
    "bbox": [
      73,
      99,
      382,
      15
    ],
    "text": "under the policy issued to him the Board shall issue such",
    "mean_p_confidence": 0.84
  },
  {
    "page_number": 6,
    "bbox": [
      72,
      120,
      219,
      12
    ],
    "text": "contributor a notice to that effect,",
    "mean_p_confidence": 0.78
  },
  {
    "page_number": 6,
    "bbox": [
      84,
      140,
      373,
      30
    ],
    "text": "(8) A conttibutor shall have the ight to appeal to the",
    "mean_p_confidence": 0.74
  },
  {
    "page_number": 6,
    "bbox": [
      72,
      164,
      425,
      16
    ],
    "text": "Board to validate his policy and the Board shall validate ~~",
    "mean_p_confidence": 0.74
  },
  {
    "page_number": 6,
    "bbox": [
      72,
      181,
      381,
      15
    ],
    "text": "the policy if {t is satisied that the reasons for failure to pay",
    "mean_p_confidence": 0.77
  },
  {
    "page_number": 6,
    "bbox": [
      72,
      197,
      381,
      16
    ],
    "text": "the instalments were beyond the control of the contributor.",
    "mean_p_confidence": 0.79
  },
  {
    "page_number": 6,
    "bbox": [
      71,
      226,
      386,
      17
    ],
    "text": "__ 4) Where the Board decides to validate a policy the",
    "mean_p_confidence": 0.65
  },
  {
    "page_number": 6,
    "bbox": [
      72,
      243,
      387,
      12
    ],
    "text": "contributor shall be informed of the date before -which the,",
    "mean_p_confidence": 0.75
  },
  {
    "page_number": 6,
    "bbox": [
      73,
      260,
      379,
      14
    ],
    "text": "arrears of instalments will have to be pald. The date of such",
    "mean_p_confidence": 0.87
  },
  {
    "page_number": 6,
    "bbox": [
      72,
      276,
      353,
      14
    ],
    "text": "payment shall be the date of validation of the policy.",
    "mean_p_confidence": 0.84
  },
  {
    "page_number": 6,
    "bbox": [
      89,
      304,
      362,
      15
    ],
    "text": "(5) Any contrlbutor aggrieved by the decision of the",
    "mean_p_confidence": 0.69
  },
  {
    "page_number": 6,
    "bbox": [
      72,
      320,
      381,
      28
    ],
    "text": "Board shall have a right to appeal to the Secretaty of the",
    "mean_p_confidence": 0.8
  },
  {
    "page_number": 6,
    "bbox": [
      73,
      337,
      378,
      14
    ],
    "text": "Ministry of the Minister whose decision shall be final and",
    "mean_p_confidence": 0.8
  },
  {
    "page_number": 6,
    "bbox": [
      69,
      347,
      340,
      27
    ],
    "text": "coneluaive, . .",
    "mean_p_confidence": 0.18
  },
  {
    "page_number": 6,
    "bbox": [
      86,
      386,
      427,
      14
    ],
    "text": "17, The award ot benefit under the Scheme to any o- Board to",
    "mean_p_confidence": 0.64
  },
  {
    "page_number": 6,
    "bbox": [
      73,
      402,
      448,
      15
    ],
    "text": "tributor shall be determined by the Board in accordance determine",
    "mean_p_confidence": 0.82
  },
  {
    "page_number": 6,
    "bbox": [
      73,
      414,
      430,
      21
    ],
    "text": "with the Scheme and the regulations made to give effect 5",
    "mean_p_confidence": 0.79
  },
  {
    "page_number": 6,
    "bbox": [
      70,
      436,
      335,
      11
    ],
    "text": "to the Scheme. .",
    "mean_p_confidence": 0.53
  },
  {
    "page_number": 6,
    "bbox": [
      86,
      467,
      421,
      17
    ],
    "text": "18. (1) Any contributor who is not satisfled with the appeai",
    "mean_p_confidence": 0.69
  },
  {
    "page_number": 6,
    "bbox": [
      72,
      484,
      380,
      14
    ],
    "text": "award of benefit determined by the Boord may, within",
    "mean_p_confidence": 0.77
  },
  {
    "page_number": 6,
    "bbox": [
      73,
      500,
      377,
      15
    ],
    "text": "thirty days of receiving the notice of such award, make an",
    "mean_p_confidence": 0.84
  },
  {
    "page_number": 6,
    "bbox": [
      73,
      517,
      439,
      15
    ],
    "text": "appeal to the Secretary of the Ministry of the Minister .",
    "mean_p_confidence": 0.79
  },
  {
    "page_number": 6,
    "bbox": [
      72,
      534,
      212,
      14
    ],
    "text": "stating the grounds of bis appeal.",
    "mean_p_confidence": 0.78
  },
  {
    "page_number": 6,
    "bbox": [
      89,
      561,
      362,
      15
    ],
    "text": "(2) The decision of the Secretary of the Ministry of the",
    "mean_p_confidence": 0.8
  },
  {
    "page_number": 6,
    "bbox": [
      72,
      578,
      348,
      15
    ],
    "text": "Minister on such appeal shall be fins! and conclusive.",
    "mean_p_confidence": 0.72
  },
  {
    "page_number": 6,
    "bbox": [
      89,
      605,
      361,
      16
    ],
    "text": "(8) The Secretary to the Ministry of the Minister shall",
    "mean_p_confidence": 0.84
  },
  {
    "page_number": 6,
    "bbox": [
      72,
      622,
      379,
      15
    ],
    "text": "communicate ta the appellant and the Bosrd, his decision",
    "mean_p_confidence": 0.77
  },
  {
    "page_number": 6,
    "bbox": [
      72,
      638,
      378,
      16
    ],
    "text": "on an appeal made to him under subsection (5) of section",
    "mean_p_confidence": 0.87
  },
  {
    "page_number": 6,
    "bbox": [
      73,
      655,
      378,
      17
    ],
    "text": "16 or subsection (1) of this section. It shall be the duty of",
    "mean_p_confidence": 0.84
  },
  {
    "page_number": 6,
    "bbox": [
      72,
      671,
      395,
      16
    ],
    "text": "the Board to give effect to.every such decision. .",
    "mean_p_confidence": 0.7
  },
  {
    "page_number": 6,
    "bbox": [
      67,
      706,
      429,
      21
    ],
    "text": "+ 1% No pension, gratuity or allowance payable from the 5,",
    "mean_p_confidence": 0.7
  },
  {
    "page_number": 6,
    "bbox": [
      72,
      728,
      442,
      15
    ],
    "text": "Scheme shall be assigned or transferred, and every assign- gratully",
    "mean_p_confidence": 0.66
  },
  {
    "page_number": 6,
    "bbox": [
      72,
      744,
      452,
      20
    ],
    "text": "ment or transfer shall be absolutely null and void and of Silowence",
    "mean_p_confidence": 0.76
  },
  {
    "page_number": 6,
    "bbox": [
      73,
      763,
      447,
      32
    ],
    "text": "no effect. No such pension or gratuity or allowance shall pop aet",
    "mean_p_confidence": 0.71
  },
  {
    "page_number": 6,
    "bbox": [
      73,
      789,
      445,
      16
    ],
    "text": "be attached or taken in execution on account of any debt ot levied",
    "mean_p_confidence": 0.82
  },
  {
    "page_number": 6,
    "bbox": [
      73,
      808,
      428,
      18
    ],
    "text": "or payment due by the person to whom such pension or \"",
    "mean_p_confidence": 0.77
  },
  {
    "page_number": 6,
    "bbox": [
      73,
      831,
      276,
      16
    ],
    "text": "sratuity or allowance ls payable. |.",
    "mean_p_confidence": 0.39
  },
  {
    "page_number": 7,
    "bbox": [
      171,
      24,
      420,
      14
    ],
    "text": "6 Fishermen's Pension and Social Security Benefit Scheme, -",
    "mean_p_confidence": 0.72
  },
  {
    "page_number": 7,
    "bbox": [
      301,
      40,
      120,
      14
    ],
    "text": "Act, No, 23-0f 1990",
    "mean_p_confidence": 0.7
  },
  {
    "page_number": 7,
    "bbox": [
      171,
      69,
      223,
      15
    ],
    "text": "~ a+ BART Ht",
    "mean_p_confidence": 0.44
  },
  {
    "page_number": 7,
    "bbox": [
      182,
      100,
      248,
      17
    ],
    "text": "~ Advisory COnROTTTER",
    "mean_p_confidence": 0.21
  },
  {
    "page_number": 7,
    "bbox": [
      72,
      134,
      483,
      17
    ],
    "text": "The oe Hf 28. There shall be an Advisory Committee (hereinatter",
    "mean_p_confidence": 0.61
  },
  {
    "page_number": 7,
    "bbox": [
      73,
      157,
      482,
      15
    ],
    "text": "Commitiee. referred to as the Committee\") which shall consist of",
    "mean_p_confidence": 0.61
  },
  {
    "page_number": 7,
    "bbox": [
      137,
      175,
      429,
      18
    ],
    "text": ", . the following members ~- 4",
    "mean_p_confidence": 0.45
  },
  {
    "page_number": 7,
    "bbox": [
      70,
      207,
      478,
      15
    ],
    "text": "= (a) six ex officio. members, nomely ~ .",
    "mean_p_confidence": 0.65
  },
  {
    "page_number": 7,
    "bbox": [
      223,
      233,
      334,
      17
    ],
    "text": "() Chairman of the Agricultural Insurance Board",
    "mean_p_confidence": 0.75
  },
  {
    "page_number": 7,
    "bbox": [
      262,
      252,
      295,
      12
    ],
    "text": "who shall be the Chairman of the Committee.",
    "mean_p_confidence": 0.8
  },
  {
    "page_number": 7,
    "bbox": [
      211,
      277,
      323,
      18
    ],
    "text": ". @) Director of Fiskeries or his representative",
    "mean_p_confidence": 0.61
  },
  {
    "page_number": 7,
    "bbox": [
      218,
      307,
      365,
      19
    ],
    "text": "Gi) Director of Penstons or his representative =",
    "mean_p_confidence": 0.66
  },
  {
    "page_number": 7,
    "bbox": [
      220,
      334,
      335,
      15
    ],
    "text": "(iv) the Chief Actuary of the Insurance Corpora",
    "mean_p_confidence": 0.63
  },
  {
    "page_number": 7,
    "bbox": [
      179,
      351,
      371,
      16
    ],
    "text": "- tion of Sei Lanka or his representative;",
    "mean_p_confidence": 0.66
  },
  {
    "page_number": 7,
    "bbox": [
      222,
      382,
      335,
      16
    ],
    "text": "(v) the Superintendent of the Department of the",
    "mean_p_confidence": 0.73
  },
  {
    "page_number": 7,
    "bbox": [
      249,
      399,
      307,
      16
    ],
    "text": ". Employees Provident Fund of the Central",
    "mean_p_confidence": 0.67
  },
  {
    "page_number": 7,
    "bbox": [
      266,
      416,
      276,
      14
    ],
    "text": "Bank of Sri Lanka or his representative;",
    "mean_p_confidence": 0.8
  },
  {
    "page_number": 7,
    "bbox": [
      222,
      441,
      334,
      22
    ],
    "text": "(1) the Commiscioner of Labour of his representa-",
    "mean_p_confidence": 0.71
  },
  {
    "page_number": 7,
    "bbox": [
      266,
      467,
      31,
      12
    ],
    "text": "tive;",
    "mean_p_confidence": 0.4
  },
  {
    "page_number": 7,
    "bbox": [
      189,
      498,
      286,
      14
    ],
    "text": "{(b) six members, nominated as follows :",
    "mean_p_confidence": 0.56
  },
  {
    "page_number": 7,
    "bbox": [
      189,
      525,
      368,
      17
    ],
    "text": "_ @) two membors nominated by the Minister from",
    "mean_p_confidence": 0.59
  },
  {
    "page_number": 7,
    "bbox": [
      268,
      547,
      181,
      17
    ],
    "text": "the Ministry in his charge;",
    "mean_p_confidence": 0.79
  },
  {
    "page_number": 7,
    "bbox": [
      173,
      578,
      384,
      18
    ],
    "text": ". Gi) one member nominated by the Minister from",
    "mean_p_confidence": 0.66
  },
  {
    "page_number": 7,
    "bbox": [
      174,
      598,
      384,
      19
    ],
    "text": "+ (| + the General Treasury in consultation with",
    "mean_p_confidence": 0.6
  },
  {
    "page_number": 7,
    "bbox": [
      211,
      618,
      380,
      16
    ],
    "text": ", the Minister in charge of the subject of =~",
    "mean_p_confidence": 0.73
  },
  {
    "page_number": 7,
    "bbox": [
      174,
      632,
      294,
      31
    ],
    "text": "a Finance ; co",
    "mean_p_confidence": 0.34
  },
  {
    "page_number": 7,
    "bbox": [
      226,
      667,
      365,
      21
    ],
    "text": "{iil} two members nominated by the Minister from",
    "mean_p_confidence": 0.72
  },
  {
    "page_number": 7,
    "bbox": [
      270,
      692,
      288,
      17
    ],
    "text": "the Agricultural Insurance Board in consul-",
    "mean_p_confidence": 0.74
  },
  {
    "page_number": 7,
    "bbox": [
      176,
      713,
      415,
      15
    ],
    "text": ". tation with the Minister in charge of the",
    "mean_p_confidence": 0.67
  },
  {
    "page_number": 7,
    "bbox": [
      177,
      735,
      316,
      15
    ],
    "text": ". subject of Agricultural Insurance ;",
    "mean_p_confidence": 0.58
  },
  {
    "page_number": 7,
    "bbox": [
      227,
      760,
      331,
      22
    ],
    "text": "{iv) one member nominated by the Minister from",
    "mean_p_confidence": 0.69
  },
  {
    "page_number": 7,
    "bbox": [
      271,
      788,
      287,
      15
    ],
    "text": "among persons who have a wide knowledge",
    "mean_p_confidence": 0.83
  },
  {
    "page_number": 7,
    "bbox": [
      271,
      808,
      286,
      15
    ],
    "text": "and experience in social security beneft",
    "mean_p_confidence": 0.66
  },
  {
    "page_number": 7,
    "bbox": [
      271,
      826,
      256,
      15
    ],
    "text": "schemes, : :",
    "mean_p_confidence": 0.21
  },
  {
    "page_number": 8,
    "bbox": [
      80,
      31,
      377,
      15
    ],
    "text": "Fishermen's Pension and Social Security Benefit Scheme 7",
    "mean_p_confidence": 0.81
  },
  {
    "page_number": 8,
    "bbox": [
      203,
      49,
      119,
      13
    ],
    "text": "Act, No. 23 of 1990",
    "mean_p_confidence": 0.78
  },
  {
    "page_number": 8,
    "bbox": [
      85,
      80,
      442,
      15
    ],
    "text": "21 (1) A person shall be disqualified from being Qualifica.",
    "mean_p_confidence": 0.65
  },
  {
    "page_number": 8,
    "bbox": [
      70,
      95,
      454,
      17
    ],
    "text": "nominated or from continuing to be a member of the Honsand",
    "mean_p_confidence": 0.69
  },
  {
    "page_number": 8,
    "bbox": [
      66,
      106,
      458,
      27
    ],
    "text": "Committee + Memure of",
    "mean_p_confidence": 0.36
  },
  {
    "page_number": 8,
    "bbox": [
      299,
      132,
      205,
      10
    ],
    "text": ": ofthe",
    "mean_p_confidence": 0.27
  },
  {
    "page_number": 8,
    "bbox": [
      90,
      137,
      437,
      33
    ],
    "text": "(a) If he is a Member of Parliament or a Member of a Bombers",
    "mean_p_confidence": 0.81
  },
  {
    "page_number": 8,
    "bbox": [
      177,
      157,
      325,
      9
    ],
    "text": "i : the",
    "mean_p_confidence": 0.28
  },
  {
    "page_number": 8,
    "bbox": [
      98,
      159,
      389,
      18
    ],
    "text": "- Provinciak Council ; or ee",
    "mean_p_confidence": 0.36
  },
  {
    "page_number": 8,
    "bbox": [
      89,
      180,
      445,
      17
    ],
    "text": "() if he has any such nancial or other tnterest as 1s Comnuttes,",
    "mean_p_confidence": 0.62
  },
  {
    "page_number": 8,
    "bbox": [
      126,
      200,
      325,
      14
    ],
    "text": "likely to affect prejudicially the discharge by him",
    "mean_p_confidence": 0.84
  },
  {
    "page_number": 8,
    "bbox": [
      126,
      216,
      303,
      17
    ],
    "text": "of his functions as such member. -.",
    "mean_p_confidence": 0.74
  },
  {
    "page_number": 8,
    "bbox": [
      74,
      244,
      376,
      14
    ],
    "text": "> (2) Every nominated member of the Committee shall,",
    "mean_p_confidence": 0.8
  },
  {
    "page_number": 8,
    "bbox": [
      72,
      260,
      377,
      14
    ],
    "text": "unless he vacates office earlier by death, resignation or re-",
    "mean_p_confidence": 0.79
  },
  {
    "page_number": 8,
    "bbox": [
      72,
      277,
      435,
      14
    ],
    "text": "moval hold office for # period of three years. .",
    "mean_p_confidence": 0.63
  },
  {
    "page_number": 8,
    "bbox": [
      89,
      305,
      360,
      13
    ],
    "text": "(3) Where a nominated member of the Committee",
    "mean_p_confidence": 0.82
  },
  {
    "page_number": 8,
    "bbox": [
      72,
      326,
      378,
      13
    ],
    "text": "vacates office earlier as aforesaid, the Minister shall nomi-",
    "mean_p_confidence": 0.83
  },
  {
    "page_number": 8,
    "bbox": [
      72,
      346,
      377,
      13
    ],
    "text": "-nate another person fn his place, having regard fo the pro-",
    "mean_p_confidence": 0.76
  },
  {
    "page_number": 8,
    "bbox": [
      73,
      366,
      406,
      13
    ],
    "text": "visions of section 20(b), and such member shall hold office .",
    "mean_p_confidence": 0.81
  },
  {
    "page_number": 8,
    "bbox": [
      74,
      386,
      377,
      14
    ],
    "text": "during the unexpired period of the member whom he suc",
    "mean_p_confidence": 0.71
  },
  {
    "page_number": 8,
    "bbox": [
      70,
      403,
      269,
      22
    ],
    "text": "ceeds. .",
    "mean_p_confidence": 0.23
  },
  {
    "page_number": 8,
    "bbox": [
      88,
      434,
      363,
      14
    ],
    "text": "(4) If the Chairmen for any reason ts unable to per",
    "mean_p_confidence": 0.73
  },
  {
    "page_number": 8,
    "bbox": [
      74,
      454,
      376,
      14
    ],
    "text": "form the duties.of his office the person who for the time",
    "mean_p_confidence": 0.84
  },
  {
    "page_number": 8,
    "bbox": [
      72,
      474,
      387,
      15
    ],
    "text": "wing acts as the Chairman of the Agricultural Insurance ~",
    "mean_p_confidence": 0.7
  },
  {
    "page_number": 8,
    "bbox": [
      71,
      493,
      384,
      14
    ],
    "text": "Board shall act os the Chairman of the Committee and,",
    "mean_p_confidence": 0.77
  },
  {
    "page_number": 8,
    "bbox": [
      71,
      514,
      379,
      14
    ],
    "text": "shall be deemed to be a member of the Committee while",
    "mean_p_confidence": 0.81
  },
  {
    "page_number": 8,
    "bbox": [
      71,
      537,
      389,
      15
    ],
    "text": "he so acts, noe",
    "mean_p_confidence": 0.52
  },
  {
    "page_number": 8,
    "bbox": [
      90,
      564,
      360,
      15
    ],
    "text": "(5) Jf any nominated member of the Committee is tem-",
    "mean_p_confidence": 0.8
  },
  {
    "page_number": 8,
    "bbox": [
      73,
      580,
      473,
      16
    ],
    "text": "porarily unable to discharge his functions on account of .",
    "mean_p_confidence": 0.71
  },
  {
    "page_number": 8,
    "bbox": [
      73,
      597,
      377,
      13
    ],
    "text": "ill-health or absence from Sti Lanka or any other cause",
    "mean_p_confidence": 0.8
  },
  {
    "page_number": 8,
    "bbox": [
      74,
      613,
      377,
      15
    ],
    "text": "the Minister may, having regard to the proviatons of sec-",
    "mean_p_confidence": 0.84
  },
  {
    "page_number": 8,
    "bbox": [
      73,
      630,
      364,
      15
    ],
    "text": "Hon 20(b), nominate another person to act in his place.",
    "mean_p_confidence": 0.83
  },
  {
    "page_number": 8,
    "bbox": [
      90,
      658,
      361,
      16
    ],
    "text": "(6) The Minister may. if he thinks it expedient to do uo, \"_,",
    "mean_p_confidence": 0.69
  },
  {
    "page_number": 8,
    "bbox": [
      71,
      674,
      381,
      18
    ],
    "text": "by Order publiched in the Gazette remove any nominated",
    "mean_p_confidence": 0.79
  },
  {
    "page_number": 8,
    "bbox": [
      73,
      691,
      460,
      14
    ],
    "text": "member of the Committee without assigning any reason -",
    "mean_p_confidence": 0.72
  },
  {
    "page_number": 8,
    "bbox": [
      72,
      707,
      380,
      14
    ],
    "text": "therefor and such removal shall not be celled in question",
    "mean_p_confidence": 0.75
  },
  {
    "page_number": 8,
    "bbox": [
      71,
      726,
      473,
      15
    ],
    "text": "in any court, .",
    "mean_p_confidence": 0.6
  },
  {
    "page_number": 8,
    "bbox": [
      89,
      753,
      413,
      16
    ],
    "text": "(1) Any nominated member of the Committee may, at ~~",
    "mean_p_confidence": 0.7
  },
  {
    "page_number": 8,
    "bbox": [
      71,
      769,
      404,
      17
    ],
    "text": "any titpe resign his office by letter addressed to the Minister. -",
    "mean_p_confidence": 0.72
  },
  {
    "page_number": 8,
    "bbox": [
      76,
      797,
      428,
      22
    ],
    "text": "(8) Any member of the Committes who vacates office",
    "mean_p_confidence": 0.58
  },
  {
    "page_number": 8,
    "bbox": [
      73,
      819,
      398,
      15
    ],
    "text": "other than a member who is zemoved from office shall. be ~",
    "mean_p_confidence": 0.74
  },
  {
    "page_number": 8,
    "bbox": [
      73,
      837,
      272,
      14
    ],
    "text": "eligible to be reappointed. .",
    "mean_p_confidence": 0.64
  },
  {
    "page_number": 9,
    "bbox": [
      174,
      28,
      411,
      14
    ],
    "text": "8 Fishermen's Pension and Socal Security Benefit Schenie - *",
    "mean_p_confidence": 0.44
  },
  {
    "page_number": 9,
    "bbox": [
      303,
      45,
      120,
      14
    ],
    "text": "Act, No, 23 of 1990",
    "mean_p_confidence": 0.73
  },
  {
    "page_number": 9,
    "bbox": [
      78,
      50,
      153,
      31
    ],
    "text": "Powere :",
    "mean_p_confidence": 0.36
  },
  {
    "page_number": 9,
    "bbox": [
      76,
      69,
      480,
      29
    ],
    "text": "Eee, 2% The Committee may exercise all or any of the",
    "mean_p_confidence": 0.75
  },
  {
    "page_number": 9,
    "bbox": [
      175,
      95,
      133,
      14
    ],
    "text": "following powers:",
    "mean_p_confidence": 0.59
  },
  {
    "page_number": 9,
    "bbox": [
      191,
      118,
      364,
      15
    ],
    "text": "(@) to advise the Boerd on such matters relating to the",
    "mean_p_confidence": 0.8
  },
  {
    "page_number": 9,
    "bbox": [
      188,
      135,
      368,
      14
    ],
    "text": "management, operation and implementation of the",
    "mean_p_confidence": 0.67
  },
  {
    "page_number": 9,
    "bbox": [
      227,
      151,
      329,
      15
    ],
    "text": "Scheme as may irom time to time be referred to",
    "mean_p_confidence": 0.82
  },
  {
    "page_number": 9,
    "bbox": [
      127,
      168,
      210,
      15
    ],
    "text": ". _ #t by the Board;",
    "mean_p_confidence": 0.47
  },
  {
    "page_number": 9,
    "bbox": [
      189,
      191,
      371,
      16
    ],
    "text": "() to advie the Board with regard to making rules of",
    "mean_p_confidence": 0.78
  },
  {
    "page_number": 9,
    "bbox": [
      225,
      209,
      85,
      13
    ],
    "text": "the Board ; -",
    "mean_p_confidence": 0.66
  },
  {
    "page_number": 9,
    "bbox": [
      136,
      232,
      423,
      14
    ],
    "text": ": (eto formutate policies under the Scheme for the",
    "mean_p_confidence": 0.62
  },
  {
    "page_number": 9,
    "bbox": [
      149,
      249,
      411,
      14
    ],
    "text": "~ efficient management, operation and implementa-",
    "mean_p_confidence": 0.71
  },
  {
    "page_number": 9,
    "bbox": [
      225,
      265,
      130,
      13
    ],
    "text": "tion of the Scheme ;",
    "mean_p_confidence": 0.78
  },
  {
    "page_number": 9,
    "bbox": [
      189,
      288,
      371,
      14
    ],
    "text": "(@) to review the work of the Board with regard to the",
    "mean_p_confidence": 0.8
  },
  {
    "page_number": 9,
    "bbox": [
      179,
      304,
      381,
      15
    ],
    "text": "+\" management, operation and implementation of the",
    "mean_p_confidence": 0.73
  },
  {
    "page_number": 9,
    "bbox": [
      225,
      322,
      87,
      13
    ],
    "text": "Scheme ; aid.",
    "mean_p_confidence": 0.62
  },
  {
    "page_number": 9,
    "bbox": [
      189,
      344,
      371,
      15
    ],
    "text": "() to advise ond make recommendations to the Minister,",
    "mean_p_confidence": 0.81
  },
  {
    "page_number": 9,
    "bbox": [
      226,
      360,
      335,
      15
    ],
    "text": "with regard to the management, operation and",
    "mean_p_confidence": 0.77
  },
  {
    "page_number": 9,
    "bbox": [
      83,
      378,
      343,
      14
    ],
    "text": ": implementation of the Scheme,",
    "mean_p_confidence": 0.65
  },
  {
    "page_number": 9,
    "bbox": [
      75,
      401,
      483,
      29
    ],
    "text": "four 2%, The members of the Committee may be patd such",
    "mean_p_confidence": 0.72
  },
  {
    "page_number": 9,
    "bbox": [
      75,
      418,
      486,
      26
    ],
    "text": "agembers remunerstion for attending the meetings of the Committee",
    "mean_p_confidence": 0.64
  },
  {
    "page_number": 9,
    "bbox": [
      79,
      438,
      481,
      22
    ],
    "text": "ofthe uee, 88 May be determined by the Board with the approval of the",
    "mean_p_confidence": 0.67
  },
  {
    "page_number": 9,
    "bbox": [
      174,
      457,
      387,
      16
    ],
    "text": "Minister, in consultation with the Minister in charge of the",
    "mean_p_confidence": 0.86
  },
  {
    "page_number": 9,
    "bbox": [
      174,
      474,
      387,
      15
    ],
    "text": "subject of Finance. The members shall be telmbursed by the",
    "mean_p_confidence": 0.78
  },
  {
    "page_number": 9,
    "bbox": [
      174,
      490,
      386,
      15
    ],
    "text": "Board for such travelling, hotel and other expenses as they",
    "mean_p_confidence": 0.84
  },
  {
    "page_number": 9,
    "bbox": [
      174,
      506,
      387,
      16
    ],
    "text": "may incur for purposes connected with the work of the",
    "mean_p_confidence": 0.84
  },
  {
    "page_number": 9,
    "bbox": [
      79,
      525,
      201,
      11
    ],
    "text": ". Committees. ~",
    "mean_p_confidence": 0.04
  },
  {
    "page_number": 9,
    "bbox": [
      74,
      551,
      497,
      24
    ],
    "text": "Power %. The Minister may give such general or special diree- ~",
    "mean_p_confidence": 0.77
  },
  {
    "page_number": 9,
    "bbox": [
      79,
      566,
      482,
      29
    ],
    "text": "te tions in writing as to the exercise of the powers of the Com-",
    "mean_p_confidence": 0.82
  },
  {
    "page_number": 9,
    "bbox": [
      75,
      587,
      486,
      21
    ],
    "text": "in mittee and the Committee shall give effect to such dire",
    "mean_p_confidence": 0.77
  },
  {
    "page_number": 9,
    "bbox": [
      75,
      602,
      158,
      22
    ],
    "text": "relation tions,",
    "mean_p_confidence": 0.26
  },
  {
    "page_number": 9,
    "bbox": [
      79,
      618,
      288,
      10
    ],
    "text": "to the .",
    "mean_p_confidence": 0.49
  },
  {
    "page_number": 9,
    "bbox": [
      75,
      620,
      417,
      31
    ],
    "text": "Comnaittee, . .",
    "mean_p_confidence": 0.38
  },
  {
    "page_number": 9,
    "bbox": [
      338,
      650,
      62,
      11
    ],
    "text": "PART IV",
    "mean_p_confidence": 0.14
  },
  {
    "page_number": 9,
    "bbox": [
      152,
      676,
      410,
      18
    ],
    "text": ". Prammentuns Pensros ano Soctat Srounret Bewrrrr Foxo",
    "mean_p_confidence": 0.27
  },
  {
    "page_number": 9,
    "bbox": [
      80,
      704,
      480,
      16
    ],
    "text": "Fishermen's 25, (1) There shall be established a Fishermen's Penston",
    "mean_p_confidence": 0.64
  },
  {
    "page_number": 9,
    "bbox": [
      75,
      714,
      157,
      22
    ],
    "text": "Pension: .",
    "mean_p_confidence": 0.16
  },
  {
    "page_number": 9,
    "bbox": [
      80,
      725,
      482,
      20
    ],
    "text": "a and Social Security Henefit Fund (hereinafter referred to",
    "mean_p_confidence": 0.72
  },
  {
    "page_number": 9,
    "bbox": [
      76,
      739,
      206,
      31
    ],
    "text": "aay as the Fund\"),",
    "mean_p_confidence": 0.6
  },
  {
    "page_number": 9,
    "bbox": [
      77,
      763,
      372,
      31
    ],
    "text": "Benet (2) There shall be patd into the Fund",
    "mean_p_confidence": 0.66
  },
  {
    "page_number": 9,
    "bbox": [
      195,
      794,
      368,
      16
    ],
    "text": "(@) such sums of money as-may be voted from time to",
    "mean_p_confidence": 0.82
  },
  {
    "page_number": 9,
    "bbox": [
      232,
      814,
      332,
      16
    ],
    "text": "time by Parliament for the operation of the",
    "mean_p_confidence": 0.8
  },
  {
    "page_number": 9,
    "bbox": [
      233,
      836,
      292,
      16
    ],
    "text": "Scheme :",
    "mean_p_confidence": 0.55
  },
  {
    "page_number": 10,
    "bbox": [
      80,
      32,
      395,
      15
    ],
    "text": "Fishermen's Pension and Social Security Benefit Scheme 9",
    "mean_p_confidence": 0.68
  },
  {
    "page_number": 10,
    "bbox": [
      199,
      50,
      159,
      13
    ],
    "text": "Act, No: 23 of 1990 -",
    "mean_p_confidence": 0.56
  },
  {
    "page_number": 10,
    "bbox": [
      85,
      81,
      367,
      15
    ],
    "text": "(1 such sums of money s may be advanced to the",
    "mean_p_confidence": 0.78
  },
  {
    "page_number": 10,
    "bbox": [
      78,
      102,
      435,
      14
    ],
    "text": "\"Hoard from time to time by the Minister in charge :",
    "mean_p_confidence": 0.78
  },
  {
    "page_number": 10,
    "bbox": [
      65,
      122,
      386,
      14
    ],
    "text": ". of the subject of Finance for the purposes of the",
    "mean_p_confidence": 0.79
  },
  {
    "page_number": 10,
    "bbox": [
      123,
      142,
      55,
      13
    ],
    "text": "Scheme ;",
    "mean_p_confidence": 0.44
  },
  {
    "page_number": 10,
    "bbox": [
      86,
      169,
      364,
      15
    ],
    "text": "() all sums of money received by the Board in the",
    "mean_p_confidence": 0.75
  },
  {
    "page_number": 10,
    "bbox": [
      122,
      190,
      327,
      13
    ],
    "text": "exercise, performance and discharge of {ts powers,",
    "mean_p_confidence": 0.81
  },
  {
    "page_number": 10,
    "bbox": [
      123,
      210,
      337,
      14
    ],
    "text": "duties and functions under this Act; ,",
    "mean_p_confidence": 0.68
  },
  {
    "page_number": 10,
    "bbox": [
      87,
      238,
      400,
      14
    ],
    "text": "(@) all sums of money paid as -vontribuilons to the =~",
    "mean_p_confidence": 0.64
  },
  {
    "page_number": 10,
    "bbox": [
      124,
      257,
      181,
      15
    ],
    "text": "Scheme by the contributors ;",
    "mean_p_confidence": 0.78
  },
  {
    "page_number": 10,
    "bbox": [
      87,
      285,
      363,
      14
    ],
    "text": "() all sums of money received from any source as gifts",
    "mean_p_confidence": 0.81
  },
  {
    "page_number": 10,
    "bbox": [
      125,
      302,
      205,
      13
    ],
    "text": "and donations to the Fund; and",
    "mean_p_confidence": 0.74
  },
  {
    "page_number": 10,
    "bbox": [
      88,
      329,
      363,
      14
    ],
    "text": "() all sums of money earned as interest or peolits from",
    "mean_p_confidence": 0.71
  },
  {
    "page_number": 10,
    "bbox": [
      121,
      336,
      325,
      31
    ],
    "text": "investments, :",
    "mean_p_confidence": 0.41
  },
  {
    "page_number": 10,
    "bbox": [
      89,
      376,
      363,
      14
    ],
    "text": "(3) There shall be paid out of the Fund ail sums of",
    "mean_p_confidence": 0.81
  },
  {
    "page_number": 10,
    "bbox": [
      73,
      392,
      379,
      14
    ],
    "text": "money required to defray any expenditure incurred by the",
    "mean_p_confidence": 0.79
  },
  {
    "page_number": 10,
    "bbox": [
      73,
      408,
      378,
      14
    ],
    "text": "Committee and the Board in the exercise, discharge and",
    "mean_p_confidence": 0.76
  },
  {
    "page_number": 10,
    "bbox": [
      74,
      424,
      379,
      15
    ],
    "text": "Retformance of the powers, duties and functions of the",
    "mean_p_confidence": 0.81
  },
  {
    "page_number": 10,
    "bbox": [
      74,
      441,
      377,
      13
    ],
    "text": "Committee and the Board, under this Act and sll sums of",
    "mean_p_confidence": 0.82
  },
  {
    "page_number": 10,
    "bbox": [
      73,
      457,
      378,
      14
    ],
    "text": "money required to he paid out of the Fund, by or under",
    "mean_p_confidence": 0.85
  },
  {
    "page_number": 10,
    "bbox": [
      75,
      474,
      350,
      11
    ],
    "text": "this Act. .",
    "mean_p_confidence": 0.44
  },
  {
    "page_number": 10,
    "bbox": [
      89,
      508,
      448,
      17
    ],
    "text": "26, All moneys in the Fund whicn are not immediately tayestment",
    "mean_p_confidence": 0.76
  },
  {
    "page_number": 10,
    "bbox": [
      75,
      523,
      442,
      19
    ],
    "text": "required by the Board under this Act may be invested by of funds,",
    "mean_p_confidence": 0.87
  },
  {
    "page_number": 10,
    "bbox": [
      75,
      541,
      379,
      13
    ],
    "text": "the Board in such manner and in such securities as may b",
    "mean_p_confidence": 0.84
  },
  {
    "page_number": 10,
    "bbox": [
      76,
      557,
      379,
      16
    ],
    "text": "authorized by the Minister with the concurrence of the",
    "mean_p_confidence": 0.82
  },
  {
    "page_number": 10,
    "bbox": [
      75,
      574,
      286,
      15
    ],
    "text": "Minister in charge of the subject of Finance.",
    "mean_p_confidence": 0.8
  },
  {
    "page_number": 10,
    "bbox": [
      90,
      605,
      437,
      17
    ],
    "text": "2%, (1) The Bosrd may, with the eoneurrence of the Borrowing",
    "mean_p_confidence": 0.69
  },
  {
    "page_number": 10,
    "bbox": [
      76,
      622,
      433,
      14
    ],
    "text": "Minister and the Minister in cherge of the subject of power",
    "mean_p_confidence": 0.84
  },
  {
    "page_number": 10,
    "bbox": [
      76,
      634,
      430,
      22
    ],
    "text": "Finance or fn accordance with the terms of any general 96",
    "mean_p_confidence": 0.73
  },
  {
    "page_number": 10,
    "bbox": [
      77,
      654,
      381,
      16
    ],
    "text": "authority given with Uke concurrence, borrow hy way of",
    "mean_p_confidence": 0.73
  },
  {
    "page_number": 10,
    "bbox": [
      77,
      671,
      381,
      14
    ],
    "text": "overdraft or otherwise, or negotiate and obtain on credit,",
    "mean_p_confidence": 0.72
  },
  {
    "page_number": 10,
    "bbox": [
      77,
      687,
      382,
      14
    ],
    "text": "such sums as the Board may require for meeting the obliga-",
    "mean_p_confidence": 0.84
  },
  {
    "page_number": 10,
    "bbox": [
      77,
      703,
      381,
      14
    ],
    "text": "tions of the Board or carrying out the objects of the Scheme",
    "mean_p_confidence": 0.86
  },
  {
    "page_number": 10,
    "bbox": [
      77,
      721,
      99,
      12
    ],
    "text": "under this Act:",
    "mean_p_confidence": 0.69
  },
  {
    "page_number": 10,
    "bbox": [
      90,
      752,
      370,
      15
    ],
    "text": "Provided thet, the aggregate of the amounts outstanding",
    "mean_p_confidence": 0.82
  },
  {
    "page_number": 10,
    "bbox": [
      78,
      772,
      383,
      17
    ],
    "text": "in respect of the loans rafsed by the Board under this sub-",
    "mean_p_confidence": 0.81
  },
  {
    "page_number": 10,
    "bbox": [
      78,
      793,
      383,
      14
    ],
    "text": "section shall not, at any time, exceed such sum as may he",
    "mean_p_confidence": 0.84
  },
  {
    "page_number": 10,
    "bbox": [
      78,
      814,
      440,
      15
    ],
    "text": "determined by the Minister with the concurrence of the -",
    "mean_p_confidence": 0.83
  },
  {
    "page_number": 10,
    "bbox": [
      77,
      834,
      310,
      15
    ],
    "text": "Minister in charge of the siibject of Finance.",
    "mean_p_confidence": 0.75
  },
  {
    "page_number": 11,
    "bbox": [
      170,
      19,
      377,
      18
    ],
    "text": "10 Fishermen's Pension and Social Security Benefit Scheme.",
    "mean_p_confidence": 0.71
  },
  {
    "page_number": 11,
    "bbox": [
      300,
      39,
      120,
      14
    ],
    "text": "Act, No. 23 of 1890",
    "mean_p_confidence": 0.78
  },
  {
    "page_number": 11,
    "bbox": [
      155,
      71,
      400,
      14
    ],
    "text": "+ (2) The Board may with the consent of the Minister",
    "mean_p_confidence": 0.78
  },
  {
    "page_number": 11,
    "bbox": [
      129,
      87,
      426,
      17
    ],
    "text": ", given with the concurrence of the Minister in charge of the",
    "mean_p_confidence": 0.77
  },
  {
    "page_number": 11,
    "bbox": [
      102,
      103,
      453,
      16
    ],
    "text": ". subject -of Finiance borrow money otherwite than by wey",
    "mean_p_confidence": 0.57
  },
  {
    "page_number": 11,
    "bbox": [
      70,
      119,
      486,
      15
    ],
    "text": "~ of loans under-subgection (1) for all or any of the following",
    "mean_p_confidence": 0.78
  },
  {
    "page_number": 11,
    "bbox": [
      59,
      138,
      258,
      17
    ],
    "text": ". Purposesc",
    "mean_p_confidence": -0.0
  },
  {
    "page_number": 11,
    "bbox": [
      107,
      159,
      449,
      16
    ],
    "text": ": (@) the requisition or acquisition of any movable or",
    "mean_p_confidence": 0.7
  },
  {
    "page_number": 11,
    "bbox": [
      223,
      176,
      334,
      14
    ],
    "text": "immovable property required for the use of the",
    "mean_p_confidence": 0.82
  },
  {
    "page_number": 11,
    "bbox": [
      223,
      192,
      257,
      14
    ],
    "text": "Board for the purposes of the Scheme ;",
    "mean_p_confidence": 0.83
  },
  {
    "page_number": 11,
    "bbox": [
      80,
      213,
      477,
      18
    ],
    "text": "_ (%) the repayment of any money borrowed under svb-",
    "mean_p_confidence": 0.67
  },
  {
    "page_number": 11,
    "bbox": [
      223,
      232,
      74,
      13
    ],
    "text": "sectian (1).",
    "mean_p_confidence": 0.45
  },
  {
    "page_number": 11,
    "bbox": [
      75,
      259,
      481,
      19
    ],
    "text": "Finanetal | 28 - (1) The financial year of the Fund shalll be the cal-",
    "mean_p_confidence": 0.76
  },
  {
    "page_number": 11,
    "bbox": [
      76,
      279,
      255,
      16
    ],
    "text": "year Sa. endar year. .",
    "mean_p_confidence": 0.36
  },
  {
    "page_number": 11,
    "bbox": [
      186,
      304,
      372,
      14
    ],
    "text": "{2) The Board shall cituse the books of the Fund to be",
    "mean_p_confidence": 0.81
  },
  {
    "page_number": 11,
    "bbox": [
      171,
      321,
      387,
      14
    ],
    "text": "balanced as on the thirty-first day of December in each year",
    "mean_p_confidence": 0.8
  },
  {
    "page_number": 11,
    "bbox": [
      116,
      337,
      441,
      14
    ],
    "text": ". and shall befote the thirtieth day of April next, cause to be",
    "mean_p_confidence": 0.82
  },
  {
    "page_number": 11,
    "bbox": [
      66,
      353,
      493,
      15
    ],
    "text": "5 prepared an income and expenditure account end a balance",
    "mean_p_confidence": 0.76
  },
  {
    "page_number": 11,
    "bbox": [
      173,
      369,
      386,
      14
    ],
    "text": "sheet containing a summary of the asvets and liabilities of",
    "mean_p_confidence": 0.73
  },
  {
    "page_number": 11,
    "bbox": [
      171,
      386,
      387,
      14
    ],
    "text": "the Fund made upto the first-mentioned date, and.a state",
    "mean_p_confidence": 0.74
  },
  {
    "page_number": 11,
    "bbox": [
      173,
      401,
      386,
      15
    ],
    "text": "tment of investment of moneys of the Fund, indicating the",
    "mean_p_confidence": 0.85
  },
  {
    "page_number": 11,
    "bbox": [
      172,
      417,
      386,
      17
    ],
    "text": "purchase price and the market value, on the first mentioned",
    "mean_p_confidence": 0.87
  },
  {
    "page_number": 11,
    "bbox": [
      173,
      436,
      170,
      13
    ],
    "text": "date, of such investments,",
    "mean_p_confidence": 0.74
  },
  {
    "page_number": 11,
    "bbox": [
      187,
      462,
      372,
      15
    ],
    "text": "(8) The income and expenditure account and the balance",
    "mean_p_confidence": 0.79
  },
  {
    "page_number": 11,
    "bbox": [
      67,
      478,
      492,
      16
    ],
    "text": "an sheet shall be signed by the member of the Board authorized",
    "mean_p_confidence": 0.81
  },
  {
    "page_number": 11,
    "bbox": [
      149,
      497,
      277,
      14
    ],
    "text": "+ te do so by a resolution of the Board.",
    "mean_p_confidence": 0.76
  },
  {
    "page_number": 11,
    "bbox": [
      64,
      524,
      495,
      17
    ],
    "text": ": . (4) The Auditor-General shall audit the accounts of the",
    "mean_p_confidence": 0.75
  },
  {
    "page_number": 11,
    "bbox": [
      173,
      540,
      386,
      18
    ],
    "text": "Scheme every year jn accordance with, Article 154 of the",
    "mean_p_confidence": 0.82
  },
  {
    "page_number": 11,
    "bbox": [
      101,
      596,
      295,
      11
    ],
    "text": ". . PART.V",
    "mean_p_confidence": 0.4
  },
  {
    "page_number": 11,
    "bbox": [
      209,
      612,
      274,
      30
    ],
    "text": ": Gexeat :",
    "mean_p_confidence": 0.1
  },
  {
    "page_number": 11,
    "bbox": [
      81,
      643,
      479,
      21
    ],
    "text": "Reguistions, 20 (1) The Minister may make regulations in respect",
    "mean_p_confidence": 0.61
  },
  {
    "page_number": 11,
    "bbox": [
      176,
      661,
      384,
      15
    ],
    "text": "of all matters which are stated or required by this Act to",
    "mean_p_confidence": 0.82
  },
  {
    "page_number": 11,
    "bbox": [
      177,
      676,
      384,
      18
    ],
    "text": "be prescribed or in respect of which regulations are required",
    "mean_p_confidence": 0.84
  },
  {
    "page_number": 11,
    "bbox": [
      177,
      697,
      232,
      14
    ],
    "text": "by this Act to be made, including",
    "mean_p_confidence": 0.82
  },
  {
    "page_number": 11,
    "bbox": [
      194,
      724,
      367,
      20
    ],
    "text": "(a) the regulation, administration and management of",
    "mean_p_confidence": 0.81
  },
  {
    "page_number": 11,
    "bbox": [
      230,
      751,
      209,
      17
    ],
    "text": "the Scheme; .",
    "mean_p_confidence": 0.33
  },
  {
    "page_number": 11,
    "bbox": [
      180,
      775,
      382,
      18
    ],
    "text": "> {b) the qualfeations, conditions snd circumstances in",
    "mean_p_confidence": 0.64
  },
  {
    "page_number": 11,
    "bbox": [
      232,
      799,
      330,
      15
    ],
    "text": "which, and the restrictions subject to which, aly",
    "mean_p_confidence": 0.79
  },
  {
    "page_number": 11,
    "bbox": [
      233,
      820,
      316,
      18
    ],
    "text": "fisherman shall be eligible ta join the Scheme;",
    "mean_p_confidence": 0.77
  },
  {
    "page_number": 12,
    "bbox": [
      69,
      35,
      385,
      17
    ],
    "text": "Fishermens Pension and Social Security Benefit Scheme 14",
    "mean_p_confidence": 0.79
  },
  {
    "page_number": 12,
    "bbox": [
      201,
      53,
      119,
      14
    ],
    "text": "Act, No, 23 of 1990",
    "mean_p_confidence": 0.71
  },
  {
    "page_number": 12,
    "bbox": [
      86,
      80,
      367,
      14
    ],
    "text": "(c} the determination of the amount of contribution to be",
    "mean_p_confidence": 0.82
  },
  {
    "page_number": 12,
    "bbox": [
      123,
      98,
      147,
      13
    ],
    "text": "made by contributors ;",
    "mean_p_confidence": 0.69
  },
  {
    "page_number": 12,
    "bbox": [
      86,
      120,
      367,
      22
    ],
    "text": "{@) the determination of the basis cn which pensions,",
    "mean_p_confidence": 0.79
  },
  {
    "page_number": 12,
    "bbox": [
      121,
      146,
      376,
      18
    ],
    "text": "gratuities or allowances are payable to contributors .",
    "mean_p_confidence": 0.75
  },
  {
    "page_number": 12,
    "bbox": [
      78,
      167,
      170,
      14
    ],
    "text": ". under the Scheme;",
    "mean_p_confidence": 0.58
  },
  {
    "page_number": 12,
    "bbox": [
      85,
      197,
      393,
      18
    ],
    "text": "(e) conditions governing the default of payment of +",
    "mean_p_confidence": 0.7
  },
  {
    "page_number": 12,
    "bbox": [
      75,
      215,
      375,
      16
    ],
    "text": "*. contributions, surrender of policy and loss of eligt-",
    "mean_p_confidence": 0.61
  },
  {
    "page_number": 12,
    "bbox": [
      123,
      232,
      231,
      15
    ],
    "text": "bility of a contributor ; .",
    "mean_p_confidence": 0.57
  },
  {
    "page_number": 12,
    "bbox": [
      87,
      260,
      364,
      16
    ],
    "text": ") regulation of the procedure for the transaction of",
    "mean_p_confidence": 0.73
  },
  {
    "page_number": 12,
    "bbox": [
      122,
      277,
      270,
      15
    ],
    "text": "business by the Board or.the Committee ;",
    "mean_p_confidence": 0.74
  },
  {
    "page_number": 12,
    "bbox": [
      87,
      305,
      331,
      19
    ],
    "text": "(g) the termination or Jorfeifure of the polley ; and",
    "mean_p_confidence": 0.65
  },
  {
    "page_number": 12,
    "bbox": [
      87,
      335,
      363,
      17
    ],
    "text": "(h) the bssis of determining partial and total disabie-",
    "mean_p_confidence": 0.74
  },
  {
    "page_number": 12,
    "bbox": [
      124,
      356,
      35,
      9
    ],
    "text": "ment.",
    "mean_p_confidence": 0.34
  },
  {
    "page_number": 12,
    "bbox": [
      86,
      380,
      364,
      21
    ],
    "text": "(2) Every regulation made by the Minister shall be",
    "mean_p_confidence": 0.81
  },
  {
    "page_number": 12,
    "bbox": [
      72,
      404,
      378,
      13
    ],
    "text": "published in the Gazette and shall come into operation on",
    "mean_p_confidence": 0.84
  },
  {
    "page_number": 12,
    "bbox": [
      71,
      420,
      379,
      14
    ],
    "text": "the date of such publication or on such inter date as may",
    "mean_p_confidence": 0.86
  },
  {
    "page_number": 12,
    "bbox": [
      72,
      437,
      194,
      14
    ],
    "text": "Le specified in the regulation.",
    "mean_p_confidence": 0.61
  },
  {
    "page_number": 12,
    "bbox": [
      88,
      470,
      362,
      13
    ],
    "text": "(8) Every such regulation shall, as soon sis convenient",
    "mean_p_confidence": 0.74
  },
  {
    "page_number": 12,
    "bbox": [
      72,
      489,
      378,
      15
    ],
    "text": "after its publication in the Gazette, be orought before Parlia-",
    "mean_p_confidence": 0.82
  },
  {
    "page_number": 12,
    "bbox": [
      71,
      509,
      380,
      15
    ],
    "text": "ment for approval, Any regulation which is not so approved.",
    "mean_p_confidence": 0.84
  },
  {
    "page_number": 12,
    "bbox": [
      72,
      529,
      379,
      14
    ],
    "text": "shall be deemied to be rescinded as from the date of such",
    "mean_p_confidence": 0.87
  },
  {
    "page_number": 12,
    "bbox": [
      72,
      550,
      379,
      16
    ],
    "text": "disapproval but without prejudice to anything previously",
    "mean_p_confidence": 0.79
  },
  {
    "page_number": 12,
    "bbox": [
      73,
      572,
      378,
      13
    ],
    "text": "done thereunder. Notification of the date on which a regula-",
    "mean_p_confidence": 0.75
  },
  {
    "page_number": 12,
    "bbox": [
      72,
      591,
      380,
      17
    ],
    "text": "tion fs deemed to be vestinded shall be published in the",
    "mean_p_confidence": 0.81
  },
  {
    "page_number": 12,
    "bbox": [
      73,
      604,
      155,
      31
    ],
    "text": "Gazette.",
    "mean_p_confidence": 0.29
  },
  {
    "page_number": 12,
    "bbox": [
      88,
      654,
      438,
      23
    ],
    "text": "30. (4) No suit or prosecution shell lie Protection",
    "mean_p_confidence": 0.69
  },
  {
    "page_number": 12,
    "bbox": [
      90,
      675,
      416,
      33
    ],
    "text": "(a) against the Boord or the Committee for any act which action",
    "mean_p_confidence": 0.77
  },
  {
    "page_number": 12,
    "bbox": [
      126,
      702,
      377,
      17
    ],
    "text": "in good fsith is done by the Board or the Committee under",
    "mean_p_confidence": 0.78
  },
  {
    "page_number": 12,
    "bbox": [
      126,
      717,
      393,
      22
    ],
    "text": "under this Act, or sag",
    "mean_p_confidence": 0.65
  },
  {
    "page_number": 12,
    "bbox": [
      293,
      741,
      227,
      11
    ],
    "text": ". 6 direction",
    "mean_p_confidence": 0.14
  },
  {
    "page_number": 12,
    "bbox": [
      90,
      754,
      418,
      22
    ],
    "text": "(b) -agsinst any member of the Board or the Committee, ofthe",
    "mean_p_confidence": 0.67
  },
  {
    "page_number": 12,
    "bbox": [
      58,
      776,
      400,
      15
    ],
    "text": ". officer, servant or agent of the Board for any act",
    "mean_p_confidence": 0.82
  },
  {
    "page_number": 12,
    "bbox": [
      77,
      797,
      381,
      15
    ],
    "text": ": which in good faith is done or purported to be done",
    "mean_p_confidence": 0.78
  },
  {
    "page_number": 12,
    "bbox": [
      125,
      818,
      333,
      16
    ],
    "text": "by him, under this Act or on the direction of the",
    "mean_p_confidence": 0.83
  },
  {
    "page_number": 12,
    "bbox": [
      70,
      830,
      372,
      31
    ],
    "text": ": Boord, .",
    "mean_p_confidence": 0.44
  },
  {
    "page_number": 13,
    "bbox": [
      176,
      25,
      385,
      14
    ],
    "text": "12 Fishermen's Pension and Social Security Benefit Scheme",
    "mean_p_confidence": 0.82
  },
  {
    "page_number": 13,
    "bbox": [
      81,
      42,
      346,
      16
    ],
    "text": ": Act, No. 28 of 1090",
    "mean_p_confidence": 0.59
  },
  {
    "page_number": 13,
    "bbox": [
      190,
      68,
      372,
      17
    ],
    "text": "(@) Any expenses. incurred by such person as ts referred",
    "mean_p_confidence": 0.75
  },
  {
    "page_number": 13,
    "bbox": [
      176,
      89,
      386,
      16
    ],
    "text": "to in subsection (1) in any suit or prosecution brought",
    "mean_p_confidence": 0.77
  },
  {
    "page_number": 13,
    "bbox": [
      69,
      109,
      493,
      18
    ],
    "text": ". against him before any Court in respect of any act which",
    "mean_p_confidence": 0.76
  },
  {
    "page_number": 13,
    "bbox": [
      73,
      131,
      500,
      16
    ],
    "text": ". in doneby him under this Act or on the direction of the",
    "mean_p_confidence": 0.78
  },
  {
    "page_number": 13,
    "bbox": [
      176,
      154,
      387,
      14
    ],
    "text": "Board, shall, if the Court holds that the act was dons in",
    "mean_p_confidence": 0.82
  },
  {
    "page_number": 13,
    "bbox": [
      176,
      175,
      230,
      14
    ],
    "text": "good inith be paid out of the Fund.",
    "mean_p_confidence": 0.71
  },
  {
    "page_number": 13,
    "bbox": [
      78,
      205,
      484,
      26
    ],
    "text": "Offtencus. , 31, Every person who contravenes or fails to comply",
    "mean_p_confidence": 0.67
  },
  {
    "page_number": 13,
    "bbox": [
      85,
      232,
      478,
      16
    ],
    "text": ". with any provision of thfs Act, or of any regulation made",
    "mean_p_confidence": 0.78
  },
  {
    "page_number": 13,
    "bbox": [
      177,
      253,
      386,
      16
    ],
    "text": "thereunder shall be guilty of an offence and shall on convic-",
    "mean_p_confidence": 0.78
  },
  {
    "page_number": 13,
    "bbox": [
      177,
      274,
      386,
      15
    ],
    "text": "tion before a Magistrate be able to imprisonment of either",
    "mean_p_confidence": 0.79
  },
  {
    "page_number": 13,
    "bbox": [
      178,
      295,
      384,
      15
    ],
    "text": "description for a term not exceeding six months or to a fre",
    "mean_p_confidence": 0.83
  },
  {
    "page_number": 13,
    "bbox": [
      176,
      314,
      386,
      17
    ],
    "text": "not exceeding one thousand five hundred rupees or to both",
    "mean_p_confidence": 0.78
  },
  {
    "page_number": 13,
    "bbox": [
      178,
      338,
      186,
      14
    ],
    "text": "such imprisonment and fine.",
    "mean_p_confidence": 0.37
  },
  {
    "page_number": 13,
    "bbox": [
      82,
      362,
      481,
      30
    ],
    "text": "Faro 32 In the event of any inconsistency between the Sinhala",
    "mean_p_confidence": 0.74
  },
  {
    "page_number": 13,
    "bbox": [
      82,
      381,
      482,
      25
    ],
    "text": "prevail, and Tamil texts of this Act, the Sinhala text shalt prevail.",
    "mean_p_confidence": 0.79
  },
  {
    "page_number": 13,
    "bbox": [
      87,
      403,
      56,
      9
    ],
    "text": "incase of",
    "mean_p_confidence": 0.43
  },
  {
    "page_number": 13,
    "bbox": [
      87,
      414,
      77,
      12
    ],
    "text": "inconsistency.",
    "mean_p_confidence": 0.45
  },
  {
    "page_number": 13,
    "bbox": [
      86,
      436,
      479,
      14
    ],
    "text": "Tnterpretation 322,_In this Act unless the context otherwise requires",
    "mean_p_confidence": 0.7
  },
  {
    "page_number": 13,
    "bbox": [
      194,
      451,
      372,
      17
    ],
    "text": "prescribed means prescribed by regulation made under",
    "mean_p_confidence": 0.77
  },
  {
    "page_number": 13,
    "bbox": [
      234,
      470,
      55,
      12
    ],
    "text": "this Act.",
    "mean_p_confidence": 0.59
  },
  {
    "page_number": 13,
    "bbox": [
      298,
      495,
      260,
      16
    ],
    "text": "+, Semepour (Section 11)",
    "mean_p_confidence": 0.39
  },
  {
    "page_number": 13,
    "bbox": [
      100,
      522,
      402,
      14
    ],
    "text": "c . Order of relatives by blood in the order of nriority",
    "mean_p_confidence": 0.73
  },
  {
    "page_number": 13,
    "bbox": [
      197,
      546,
      284,
      11
    ],
    "text": "(1) Sone .",
    "mean_p_confidence": 0.4
  },
  {
    "page_number": 13,
    "bbox": [
      197,
      564,
      81,
      11
    ],
    "text": "(2) Daughters",
    "mean_p_confidence": 0.55
  },
  {
    "page_number": 13,
    "bbox": [
      85,
      582,
      196,
      11
    ],
    "text": "7 (8) Grendsone",
    "mean_p_confidence": 0.24
  },
  {
    "page_number": 13,
    "bbox": [
      198,
      600,
      119,
      12
    ],
    "text": "@) Grand-daughters",
    "mean_p_confidence": 0.32
  },
  {
    "page_number": 13,
    "bbox": [
      199,
      618,
      62,
      13
    ],
    "text": "(8) Father",
    "mean_p_confidence": 0.54
  },
  {
    "page_number": 13,
    "bbox": [
      200,
      635,
      64,
      11
    ],
    "text": "(8) Mother",
    "mean_p_confidence": 0.54
  },
  {
    "page_number": 13,
    "bbox": [
      165,
      653,
      107,
      12
    ],
    "text": ". (7) Brothers",
    "mean_p_confidence": 0.34
  },
  {
    "page_number": 13,
    "bbox": [
      201,
      671,
      60,
      10
    ],
    "text": "(8) Sisters",
    "mean_p_confidence": 0.5
  },
  {
    "page_number": 13,
    "bbox": [
      202,
      688,
      60,
      11
    ],
    "text": "@) Uncles",
    "mean_p_confidence": 0.48
  },
  {
    "page_number": 13,
    "bbox": [
      166,
      706,
      94,
      12
    ],
    "text": "+ (19) Aunts",
    "mean_p_confidence": 0.43
  },
  {
    "page_number": 13,
    "bbox": [
      198,
      724,
      78,
      11
    ],
    "text": "UD Nephews",
    "mean_p_confidence": 0.34
  },
  {
    "page_number": 13,
    "bbox": [
      197,
      741,
      67,
      10
    ],
    "text": "412) ieces,",
    "mean_p_confidence": 0.3
  }
]